{
"meta":{"test_sets":[],"test_metrics":[],"learn_metrics":[{"best_value":"Min","name":"Logloss"}],"launch_mode":"Train","parameters":"","iteration_count":1000,"learn_sets":["learn"],"name":"experiment"},
"iterations":[
{"learn":[0.683599361],"iteration":0,"passed_time":0.0543572902,"remaining_time":54.30293291},
{"learn":[0.6756874973],"iteration":1,"passed_time":0.05617008045,"remaining_time":28.02887014},
{"learn":[0.6661586513],"iteration":2,"passed_time":0.05797882894,"remaining_time":19.26829748},
{"learn":[0.6568112865],"iteration":3,"passed_time":0.05975957681,"remaining_time":14.88013463},
{"learn":[0.6489810672],"iteration":4,"passed_time":0.06170962011,"remaining_time":12.2802144},
{"learn":[0.6409112386],"iteration":5,"passed_time":0.06341199124,"remaining_time":10.50525321},
{"learn":[0.6330593419],"iteration":6,"passed_time":0.06518003049,"remaining_time":9.246252897},
{"learn":[0.6253281972],"iteration":7,"passed_time":0.06697040358,"remaining_time":8.304330043},
{"learn":[0.618787554],"iteration":8,"passed_time":0.06871285893,"remaining_time":7.566049244},
{"learn":[0.6119793471],"iteration":9,"passed_time":0.07038731277,"remaining_time":6.968343965},
{"learn":[0.6058317911],"iteration":10,"passed_time":0.0720971424,"remaining_time":6.482188531},
{"learn":[0.600449108],"iteration":11,"passed_time":0.07385613979,"remaining_time":6.080822176},
{"learn":[0.5951191226],"iteration":12,"passed_time":0.07552442683,"remaining_time":5.734046868},
{"learn":[0.589923094],"iteration":13,"passed_time":0.07721425602,"remaining_time":5.438089745},
{"learn":[0.585394115],"iteration":14,"passed_time":0.07881812496,"remaining_time":5.175723539},
{"learn":[0.5807949686],"iteration":15,"passed_time":0.08039716002,"remaining_time":4.944425341},
{"learn":[0.5760848067],"iteration":16,"passed_time":0.08202390447,"remaining_time":4.742911652},
{"learn":[0.572101483],"iteration":17,"passed_time":0.08360293953,"remaining_time":4.561004812},
{"learn":[0.5682467947],"iteration":18,"passed_time":0.08514822384,"remaining_time":4.396337241},
{"learn":[0.5646639943],"iteration":19,"passed_time":0.08671492529,"remaining_time":4.249031339},
{"learn":[0.5607489881],"iteration":20,"passed_time":0.08834841989,"remaining_time":4.118719194},
{"learn":[0.5573722298],"iteration":21,"passed_time":0.08994749706,"remaining_time":3.998575096},
{"learn":[0.5552681773],"iteration":22,"passed_time":0.09095468609,"remaining_time":3.863596883},
{"learn":[0.5518160469],"iteration":23,"passed_time":0.09257168032,"remaining_time":3.764581666},
{"learn":[0.5484689818],"iteration":24,"passed_time":0.09414921535,"remaining_time":3.671819399},
{"learn":[0.5452390128],"iteration":25,"passed_time":0.09572945877,"remaining_time":3.586172801},
{"learn":[0.5420188469],"iteration":26,"passed_time":0.09746703901,"remaining_time":3.512423295},
{"learn":[0.5392074113],"iteration":27,"passed_time":0.09904486571,"remaining_time":3.438271767},
{"learn":[0.5368264826],"iteration":28,"passed_time":0.1006939857,"remaining_time":3.371512416},
{"learn":[0.5340788917],"iteration":29,"passed_time":0.1022908128,"remaining_time":3.307402946},
{"learn":[0.5312530599],"iteration":30,"passed_time":0.1038953067,"remaining_time":3.247566201},
{"learn":[0.5291602396],"iteration":31,"passed_time":0.1055635938,"remaining_time":3.193298712},
{"learn":[0.5268481624],"iteration":32,"passed_time":0.1071699211,"remaining_time":3.140403446},
{"learn":[0.5248199623],"iteration":33,"passed_time":0.1087322058,"remaining_time":3.089273847},
{"learn":[0.522676704],"iteration":34,"passed_time":0.1103019073,"remaining_time":3.041181159},
{"learn":[0.520497937],"iteration":35,"passed_time":0.1119050262,"remaining_time":2.996567925},
{"learn":[0.5186410754],"iteration":36,"passed_time":0.1135021867,"remaining_time":2.954124481},
{"learn":[0.5166699521],"iteration":37,"passed_time":0.1150519711,"remaining_time":2.912631479},
{"learn":[0.5151453813],"iteration":38,"passed_time":0.1167013411,"remaining_time":2.875640737},
{"learn":[0.513370129],"iteration":39,"passed_time":0.1183843368,"remaining_time":2.841224082},
{"learn":[0.5116646673],"iteration":40,"passed_time":0.1199369546,"remaining_time":2.80535462},
{"learn":[0.5099830244],"iteration":41,"passed_time":0.1215590322,"remaining_time":2.77270364},
{"learn":[0.508693897],"iteration":42,"passed_time":0.1231109,"remaining_time":2.739933287},
{"learn":[0.5073588695],"iteration":43,"passed_time":0.124700852,"remaining_time":2.709409421},
{"learn":[0.506107244],"iteration":44,"passed_time":0.1262891373,"remaining_time":2.680136135},
{"learn":[0.5047373031],"iteration":45,"passed_time":0.1279635494,"remaining_time":2.653852743},
{"learn":[0.5030723534],"iteration":46,"passed_time":0.1295735019,"remaining_time":2.627309516},
{"learn":[0.5017169658],"iteration":47,"passed_time":0.1311643288,"remaining_time":2.601425855},
{"learn":[0.500406179],"iteration":48,"passed_time":0.1328287825,"remaining_time":2.577962696},
{"learn":[0.4991468967],"iteration":49,"passed_time":0.1344092759,"remaining_time":2.553776242},
{"learn":[0.4980275111],"iteration":50,"passed_time":0.1359201428,"remaining_time":2.529180696},
{"learn":[0.4972949776],"iteration":51,"passed_time":0.137100419,"remaining_time":2.4994461},
{"learn":[0.4962326232],"iteration":52,"passed_time":0.1386759123,"remaining_time":2.477850735},
{"learn":[0.4948382804],"iteration":53,"passed_time":0.1403509078,"remaining_time":2.458739977},
{"learn":[0.4938499367],"iteration":54,"passed_time":0.1419237761,"remaining_time":2.438508516},
{"learn":[0.4929513297],"iteration":55,"passed_time":0.1435336868,"remaining_time":2.419567863},
{"learn":[0.4920514513],"iteration":56,"passed_time":0.1451514311,"remaining_time":2.401364903},
{"learn":[0.4911105999],"iteration":57,"passed_time":0.1467521749,"remaining_time":2.383457738},
{"learn":[0.4899564622],"iteration":58,"passed_time":0.1483802944,"remaining_time":2.36653995},
{"learn":[0.4891461495],"iteration":59,"passed_time":0.1500217892,"remaining_time":2.350341364},
{"learn":[0.4883230248],"iteration":60,"passed_time":0.1516071161,"remaining_time":2.333755442},
{"learn":[0.4875187919],"iteration":61,"passed_time":0.1532783198,"remaining_time":2.318952645},
{"learn":[0.4866806607],"iteration":62,"passed_time":0.1549378567,"remaining_time":2.304393202},
{"learn":[0.485818252],"iteration":63,"passed_time":0.1565217668,"remaining_time":2.28913084},
{"learn":[0.4851972246],"iteration":64,"passed_time":0.1580873433,"remaining_time":2.27402563},
{"learn":[0.4845214456],"iteration":65,"passed_time":0.1596175439,"remaining_time":2.258830091},
{"learn":[0.4839720237],"iteration":66,"passed_time":0.1612386632,"remaining_time":2.245308549},
{"learn":[0.4834152217],"iteration":67,"passed_time":0.1628281569,"remaining_time":2.231703562},
{"learn":[0.482605068],"iteration":68,"passed_time":0.1644330675,"remaining_time":2.218654867},
{"learn":[0.4819222371],"iteration":69,"passed_time":0.1660612703,"remaining_time":2.206242591},
{"learn":[0.4812179937],"iteration":70,"passed_time":0.1677003067,"remaining_time":2.194275844},
{"learn":[0.4805957895],"iteration":71,"passed_time":0.1692829668,"remaining_time":2.18186935},
{"learn":[0.480030545],"iteration":72,"passed_time":0.1708436265,"remaining_time":2.169480024},
{"learn":[0.4794002025],"iteration":73,"passed_time":0.1724957048,"remaining_time":2.158527333},
{"learn":[0.4787052224],"iteration":74,"passed_time":0.1740291972,"remaining_time":2.146360099},
{"learn":[0.4778694169],"iteration":75,"passed_time":0.1756639002,"remaining_time":2.135703207},
{"learn":[0.4772919296],"iteration":76,"passed_time":0.1772553938,"remaining_time":2.124762708},
{"learn":[0.4767396801],"iteration":77,"passed_time":0.1788731381,"remaining_time":2.114372222},
{"learn":[0.4760417903],"iteration":78,"passed_time":0.1804569233,"remaining_time":2.103807928},
{"learn":[0.4754487594],"iteration":79,"passed_time":0.182038,"remaining_time":2.093437},
{"learn":[0.4748367439],"iteration":80,"passed_time":0.183657911,"remaining_time":2.083723706},
{"learn":[0.4743863827],"iteration":81,"passed_time":0.1852464463,"remaining_time":2.073856557},
{"learn":[0.4738969389],"iteration":82,"passed_time":0.1868496902,"remaining_time":2.064351396},
{"learn":[0.47350504],"iteration":83,"passed_time":0.1884628093,"remaining_time":2.055142064},
{"learn":[0.4729056949],"iteration":84,"passed_time":0.1900483029,"remaining_time":2.045814084},
{"learn":[0.4723479342],"iteration":85,"passed_time":0.1916252546,"remaining_time":2.03657538},
{"learn":[0.4718378604],"iteration":86,"passed_time":0.1932555408,"remaining_time":2.028072514},
{"learn":[0.4713744836],"iteration":87,"passed_time":0.1948447427,"remaining_time":2.019300061},
{"learn":[0.4709930584],"iteration":88,"passed_time":0.1964374447,"remaining_time":2.010724856},
{"learn":[0.4704982283],"iteration":89,"passed_time":0.1980101047,"remaining_time":2.002102169},
{"learn":[0.4700677859],"iteration":90,"passed_time":0.1996295989,"remaining_time":1.994102258},
{"learn":[0.4696737458],"iteration":91,"passed_time":0.2011969671,"remaining_time":1.985726588},
{"learn":[0.4694453441],"iteration":92,"passed_time":0.2024117024,"remaining_time":1.974058216},
{"learn":[0.4689425526],"iteration":93,"passed_time":0.2041368657,"remaining_time":1.967531918},
{"learn":[0.4687947327],"iteration":94,"passed_time":0.2051375129,"remaining_time":1.954204728},
{"learn":[0.4682353191],"iteration":95,"passed_time":0.2066483381,"remaining_time":1.945938517},
{"learn":[0.4678072256],"iteration":96,"passed_time":0.2082500403,"remaining_time":1.938657592},
{"learn":[0.4671825092],"iteration":97,"passed_time":0.2098052415,"remaining_time":1.93106457},
{"learn":[0.4667099762],"iteration":98,"passed_time":0.2113366505,"remaining_time":1.923376991},
{"learn":[0.4663205293],"iteration":99,"passed_time":0.2129865622,"remaining_time":1.916879059},
{"learn":[0.4659967649],"iteration":100,"passed_time":0.2145410133,"remaining_time":1.909627436},
{"learn":[0.4655851501],"iteration":101,"passed_time":0.2160608804,"remaining_time":1.902183045},
{"learn":[0.4652092921],"iteration":102,"passed_time":0.2176787497,"remaining_time":1.89570717},
{"learn":[0.4649190085],"iteration":103,"passed_time":0.2193159944,"remaining_time":1.889491644},
{"learn":[0.4645197741],"iteration":104,"passed_time":0.2208965295,"remaining_time":1.882879942},
{"learn":[0.464223048],"iteration":105,"passed_time":0.2225091069,"remaining_time":1.876633411},
{"learn":[0.4638097478],"iteration":106,"passed_time":0.2241298512,"remaining_time":1.870541656},
{"learn":[0.4634207887],"iteration":107,"passed_time":0.2257667626,"remaining_time":1.864666224},
{"learn":[0.4631993364],"iteration":108,"passed_time":0.227375465,"remaining_time":1.858637975},
{"learn":[0.462862052],"iteration":109,"passed_time":0.2289750838,"remaining_time":1.852616587},
{"learn":[0.4625481311],"iteration":110,"passed_time":0.2305520355,"remaining_time":1.846493329},
{"learn":[0.4622045403],"iteration":111,"passed_time":0.2321690297,"remaining_time":1.840768736},
{"learn":[0.4619973334],"iteration":112,"passed_time":0.233772107,"remaining_time":1.835007601},
{"learn":[0.4617055772],"iteration":113,"passed_time":0.2353713508,"remaining_time":1.829289621},
{"learn":[0.461468952],"iteration":114,"passed_time":0.2369347605,"remaining_time":1.823367505},
{"learn":[0.4611082095],"iteration":115,"passed_time":0.2384961702,"remaining_time":1.817505297},
{"learn":[0.4607945801],"iteration":116,"passed_time":0.2400744969,"remaining_time":1.81184428},
{"learn":[0.4605598045],"iteration":117,"passed_time":0.2416687823,"remaining_time":1.806371746},
{"learn":[0.4603493906],"iteration":118,"passed_time":0.2429888533,"remaining_time":1.798934284},
{"learn":[0.4598962335],"iteration":119,"passed_time":0.2445631799,"remaining_time":1.793463319},
{"learn":[0.4595034949],"iteration":120,"passed_time":0.2461572153,"remaining_time":1.788199936},
{"learn":[0.4591267942],"iteration":121,"passed_time":0.2477314586,"remaining_time":1.782854268},
{"learn":[0.4588199546],"iteration":122,"passed_time":0.2494963311,"remaining_time":1.778929125},
{"learn":[0.4585472111],"iteration":123,"passed_time":0.2510126564,"remaining_time":1.77328296},
{"learn":[0.4582929284],"iteration":124,"passed_time":0.2527703205,"remaining_time":1.769392243},
{"learn":[0.4577378017],"iteration":125,"passed_time":0.2543796479,"remaining_time":1.764506446},
{"learn":[0.4575334214],"iteration":126,"passed_time":0.2559679331,"remaining_time":1.759527603},
{"learn":[0.4571882216],"iteration":127,"passed_time":0.2575696354,"remaining_time":1.754693141},
{"learn":[0.4567993096],"iteration":128,"passed_time":0.2591834212,"remaining_time":1.749990386},
{"learn":[0.4565461866],"iteration":129,"passed_time":0.2607327472,"remaining_time":1.74490377},
{"learn":[0.4562984749],"iteration":130,"passed_time":0.2623205325,"remaining_time":1.74012628},
{"learn":[0.4560757735],"iteration":131,"passed_time":0.2638875673,"remaining_time":1.73526067},
{"learn":[0.4557527834],"iteration":132,"passed_time":0.265435935,"remaining_time":1.730322975},
{"learn":[0.4555571252],"iteration":133,"passed_time":0.2670255536,"remaining_time":1.725702459},
{"learn":[0.4552708827],"iteration":134,"passed_time":0.2686280475,"remaining_time":1.721209342},
{"learn":[0.4551058197],"iteration":135,"passed_time":0.2702324998,"remaining_time":1.716771175},
{"learn":[0.4546833072],"iteration":136,"passed_time":0.2718477857,"remaining_time":1.712442621},
{"learn":[0.4543445032],"iteration":137,"passed_time":0.2734199039,"remaining_time":1.707883748},
{"learn":[0.4539997287],"iteration":138,"passed_time":0.2749611465,"remaining_time":1.703176598},
{"learn":[0.4536788969],"iteration":139,"passed_time":0.2765503484,"remaining_time":1.698809283},
{"learn":[0.453535644],"iteration":140,"passed_time":0.2781049663,"remaining_time":1.694270681},
{"learn":[0.4533203636],"iteration":141,"passed_time":0.2796889598,"remaining_time":1.689951602},
{"learn":[0.4530262814],"iteration":142,"passed_time":0.2812669532,"remaining_time":1.685634817},
{"learn":[0.4528107001],"iteration":143,"passed_time":0.282791737,"remaining_time":1.68103977},
{"learn":[0.452423107],"iteration":144,"passed_time":0.2844251483,"remaining_time":1.677127598},
{"learn":[0.4521627528],"iteration":145,"passed_time":0.2860448509,"remaining_time":1.673166457},
{"learn":[0.4519855854],"iteration":146,"passed_time":0.2876353862,"remaining_time":1.669067921},
{"learn":[0.4518543946],"iteration":147,"passed_time":0.2892762143,"remaining_time":1.665292801},
{"learn":[0.4516922416],"iteration":148,"passed_time":0.2908911252,"remaining_time":1.661398306},
{"learn":[0.4514691947],"iteration":149,"passed_time":0.2925365367,"remaining_time":1.657707041},
{"learn":[0.4512766302],"iteration":150,"passed_time":0.2942413246,"remaining_time":1.654376719},
{"learn":[0.4510297157],"iteration":151,"passed_time":0.2958149012,"remaining_time":1.650335764},
{"learn":[0.4506135844],"iteration":152,"passed_time":0.2973829776,"remaining_time":1.646296615},
{"learn":[0.450378492],"iteration":153,"passed_time":0.2989601793,"remaining_time":1.642339686},
{"learn":[0.4502944896],"iteration":154,"passed_time":0.3000329531,"remaining_time":1.635663519},
{"learn":[0.4500850192],"iteration":155,"passed_time":0.3016676144,"remaining_time":1.632099145},
{"learn":[0.4499430919],"iteration":156,"passed_time":0.3032775668,"remaining_time":1.628426681},
{"learn":[0.4498837164],"iteration":157,"passed_time":0.3042187961,"remaining_time":1.621216622},
{"learn":[0.4497223126],"iteration":158,"passed_time":0.3057910393,"remaining_time":1.617423044},
{"learn":[0.4493626989],"iteration":159,"passed_time":0.307367616,"remaining_time":1.613679984},
{"learn":[0.4492977574],"iteration":160,"passed_time":0.3083839719,"remaining_time":1.607044425},
{"learn":[0.4491345184],"iteration":161,"passed_time":0.3099387564,"remaining_time":1.603263444},
{"learn":[0.4488572298],"iteration":162,"passed_time":0.311480999,"remaining_time":1.599445375},
{"learn":[0.4487184196],"iteration":163,"passed_time":0.3130749094,"remaining_time":1.59591844},
{"learn":[0.4483442169],"iteration":164,"passed_time":0.3146386524,"remaining_time":1.592262271},
{"learn":[0.4479351959],"iteration":165,"passed_time":0.3161333106,"remaining_time":1.588284223},
{"learn":[0.4477029086],"iteration":166,"passed_time":0.3176912202,"remaining_time":1.584651416},
{"learn":[0.4473048144],"iteration":167,"passed_time":0.3192854223,"remaining_time":1.581223044},
{"learn":[0.4470416369],"iteration":168,"passed_time":0.3209200836,"remaining_time":1.578015322},
{"learn":[0.4466764665],"iteration":169,"passed_time":0.3225001186,"remaining_time":1.574559403},
{"learn":[0.4463564437],"iteration":170,"passed_time":0.3240856955,"remaining_time":1.57115229},
{"learn":[0.446155852],"iteration":171,"passed_time":0.3256391467,"remaining_time":1.567611706},
{"learn":[0.445986715],"iteration":172,"passed_time":0.3272043898,"remaining_time":1.564150464},
{"learn":[0.4456841137],"iteration":173,"passed_time":0.3288202173,"remaining_time":1.560951146},
{"learn":[0.4454942564],"iteration":174,"passed_time":0.330412461,"remaining_time":1.557658745},
{"learn":[0.4453112198],"iteration":175,"passed_time":0.3320080381,"remaining_time":1.554401269},
{"learn":[0.4450571975],"iteration":176,"passed_time":0.3335644476,"remaining_time":1.550980454},
{"learn":[0.4449024945],"iteration":177,"passed_time":0.3353050279,"remaining_time":1.548431084},
{"learn":[0.4447215901],"iteration":178,"passed_time":0.3369277723,"remaining_time":1.545350285},
{"learn":[0.4446014236],"iteration":179,"passed_time":0.3385715588,"remaining_time":1.542381546},
{"learn":[0.4445754285],"iteration":180,"passed_time":0.3395481221,"remaining_time":1.536408354},
{"learn":[0.4444014551],"iteration":181,"passed_time":0.3411341157,"remaining_time":1.533229157},
{"learn":[0.4442410598],"iteration":182,"passed_time":0.3426691081,"remaining_time":1.529839679},
{"learn":[0.4440773308],"iteration":183,"passed_time":0.3443038111,"remaining_time":1.526912553},
{"learn":[0.4438034578],"iteration":184,"passed_time":0.3458705125,"remaining_time":1.523699825},
{"learn":[0.443629178],"iteration":185,"passed_time":0.3475056322,"remaining_time":1.520804218},
{"learn":[0.4432203113],"iteration":186,"passed_time":0.3491327933,"remaining_time":1.517887492},
{"learn":[0.4430534505],"iteration":187,"passed_time":0.3507344955,"remaining_time":1.514874523},
{"learn":[0.4428395159],"iteration":188,"passed_time":0.352318489,"remaining_time":1.5118005},
{"learn":[0.4427685354],"iteration":189,"passed_time":0.3538633983,"remaining_time":1.50857554},
{"learn":[0.442593608],"iteration":190,"passed_time":0.355500018,"remaining_time":1.505756621},
{"learn":[0.4422160381],"iteration":191,"passed_time":0.3571313042,"remaining_time":1.502927572},
{"learn":[0.4420688462],"iteration":192,"passed_time":0.3587366732,"remaining_time":1.500002566},
{"learn":[0.4418946938],"iteration":193,"passed_time":0.360291291,"remaining_time":1.496880312},
{"learn":[0.4416848956],"iteration":194,"passed_time":0.3618694094,"remaining_time":1.493871152},
{"learn":[0.4414670042],"iteration":195,"passed_time":0.3633917765,"remaining_time":1.4906479},
{"learn":[0.4412431458],"iteration":196,"passed_time":0.3650514801,"remaining_time":1.488001718},
{"learn":[0.4409391319],"iteration":197,"passed_time":0.3666904748,"remaining_time":1.48528162},
{"learn":[0.4408444102],"iteration":198,"passed_time":0.3683133025,"remaining_time":1.482507313},
{"learn":[0.4404762864],"iteration":199,"passed_time":0.3699687976,"remaining_time":1.47987519},
{"learn":[0.4403203459],"iteration":200,"passed_time":0.3715979171,"remaining_time":1.477147939},
{"learn":[0.4400525327],"iteration":201,"passed_time":0.3731330345,"remaining_time":1.474060206},
{"learn":[0.4399501054],"iteration":202,"passed_time":0.3747222781,"remaining_time":1.471200274},
{"learn":[0.4397073945],"iteration":203,"passed_time":0.3763671063,"remaining_time":1.468569689},
{"learn":[0.4392768052],"iteration":204,"passed_time":0.3779038071,"remaining_time":1.465529398},
{"learn":[0.4390562554],"iteration":205,"passed_time":0.3794721752,"remaining_time":1.462625763},
{"learn":[0.4387934954],"iteration":206,"passed_time":0.3810687523,"remaining_time":1.459843095},
{"learn":[0.4385521728],"iteration":207,"passed_time":0.3828029575,"remaining_time":1.457595877},
{"learn":[0.4383581748],"iteration":208,"passed_time":0.3843343665,"remaining_time":1.454586047},
{"learn":[0.4381908338],"iteration":209,"passed_time":0.3859282352,"remaining_time":1.451825266},
{"learn":[0.4380226102],"iteration":210,"passed_time":0.3877183583,"remaining_time":1.449809406},
{"learn":[0.43783126],"iteration":211,"passed_time":0.3893447278,"remaining_time":1.447187007},
{"learn":[0.4375796366],"iteration":212,"passed_time":0.3909720139,"remaining_time":1.444577347},
{"learn":[0.4373169675],"iteration":213,"passed_time":0.3925696327,"remaining_time":1.441867903},
{"learn":[0.4371458484],"iteration":214,"passed_time":0.3941824185,"remaining_time":1.439224179},
{"learn":[0.436890031],"iteration":215,"passed_time":0.3956843685,"remaining_time":1.436187708},
{"learn":[0.4368898192],"iteration":216,"passed_time":0.3964924281,"remaining_time":1.430661619},
{"learn":[0.4367187582],"iteration":217,"passed_time":0.3980812551,"remaining_time":1.427979548},
{"learn":[0.4366314444],"iteration":218,"passed_time":0.3996704153,"remaining_time":1.42530865},
{"learn":[0.4364865811],"iteration":219,"passed_time":0.4013742448,"remaining_time":1.423054141},
{"learn":[0.4363530394],"iteration":220,"passed_time":0.4029333628,"remaining_time":1.420294523},
{"learn":[0.4361735335],"iteration":221,"passed_time":0.4045596072,"remaining_time":1.417780966},
{"learn":[0.4360420437],"iteration":222,"passed_time":0.4061928102,"remaining_time":1.415299612},
{"learn":[0.4359266503],"iteration":223,"passed_time":0.4077067188,"remaining_time":1.412412561},
{"learn":[0.4357847897],"iteration":224,"passed_time":0.4092869205,"remaining_time":1.40976606},
{"learn":[0.4355660196],"iteration":225,"passed_time":0.410868289,"remaining_time":1.40713299},
{"learn":[0.4352867432],"iteration":226,"passed_time":0.4124829915,"remaining_time":1.404622698},
{"learn":[0.4349698442],"iteration":227,"passed_time":0.4140558597,"remaining_time":1.401978613},
{"learn":[0.4348462787],"iteration":228,"passed_time":0.4156556453,"remaining_time":1.399434509},
{"learn":[0.4346908026],"iteration":229,"passed_time":0.4173390576,"remaining_time":1.397178584},
{"learn":[0.4345645349],"iteration":230,"passed_time":0.4188995506,"remaining_time":1.394518417},
{"learn":[0.4344157634],"iteration":231,"passed_time":0.4204479183,"remaining_time":1.391827592},
{"learn":[0.4341416319],"iteration":232,"passed_time":0.4220429121,"remaining_time":1.389300058},
{"learn":[0.4339929708],"iteration":233,"passed_time":0.4236933654,"remaining_time":1.386962042},
{"learn":[0.4337228102],"iteration":234,"passed_time":0.4252899008,"remaining_time":1.384454358},
{"learn":[0.4335525719],"iteration":235,"passed_time":0.4268486854,"remaining_time":1.381832185},
{"learn":[0.4332388375],"iteration":236,"passed_time":0.4284132618,"remaining_time":1.379237632},
{"learn":[0.4329650748],"iteration":237,"passed_time":0.4299797133,"remaining_time":1.376657737},
{"learn":[0.4327382966],"iteration":238,"passed_time":0.4315729153,"remaining_time":1.3741715},
{"learn":[0.4326107446],"iteration":239,"passed_time":0.4331724508,"remaining_time":1.371712761},
{"learn":[0.4323677737],"iteration":240,"passed_time":0.4348991558,"remaining_time":1.369661657},
{"learn":[0.4321135709],"iteration":241,"passed_time":0.4365215252,"remaining_time":1.36728643},
{"learn":[0.4319945646],"iteration":242,"passed_time":0.4380956851,"remaining_time":1.364767217},
{"learn":[0.4318705728],"iteration":243,"passed_time":0.4396555114,"remaining_time":1.362211339},
{"learn":[0.4317510418],"iteration":244,"passed_time":0.4413136316,"remaining_time":1.359966497},
{"learn":[0.4315324365],"iteration":245,"passed_time":0.442846374,"remaining_time":1.357342138},
{"learn":[0.4312870735],"iteration":246,"passed_time":0.4444049919,"remaining_time":1.354805502},
{"learn":[0.4310448584],"iteration":247,"passed_time":0.4460489034,"remaining_time":1.352535384},
{"learn":[0.4309645726],"iteration":248,"passed_time":0.4476374803,"remaining_time":1.350103405},
{"learn":[0.430667224],"iteration":249,"passed_time":0.4491947649,"remaining_time":1.347584295},
{"learn":[0.4305273843],"iteration":250,"passed_time":0.4507827585,"remaining_time":1.345164487},
{"learn":[0.4302523662],"iteration":251,"passed_time":0.4523416681,"remaining_time":1.342664951},
{"learn":[0.4302396654],"iteration":252,"passed_time":0.4533564406,"remaining_time":1.33856625},
{"learn":[0.4301172609],"iteration":253,"passed_time":0.4550969793,"remaining_time":1.336623412},
{"learn":[0.4299819676],"iteration":254,"passed_time":0.456675681,"remaining_time":1.334209343},
{"learn":[0.4298262801],"iteration":255,"passed_time":0.4582976753,"remaining_time":1.331927619},
{"learn":[0.4297550045],"iteration":256,"passed_time":0.4600320889,"remaining_time":1.329976039},
{"learn":[0.4296016605],"iteration":257,"passed_time":0.4616142907,"remaining_time":1.327588386},
{"learn":[0.4293401079],"iteration":258,"passed_time":0.4632330349,"remaining_time":1.325311501},
{"learn":[0.4291286265],"iteration":259,"passed_time":0.4647974863,"remaining_time":1.322885153},
{"learn":[0.4287920226],"iteration":260,"passed_time":0.4663414789,"remaining_time":1.320407483},
{"learn":[0.4286748848],"iteration":261,"passed_time":0.4679317226,"remaining_time":1.318067219},
{"learn":[0.428571256],"iteration":262,"passed_time":0.4695279247,"remaining_time":1.315749355},
{"learn":[0.4284080895],"iteration":263,"passed_time":0.4711295019,"remaining_time":1.313451945},
{"learn":[0.4282048346],"iteration":264,"passed_time":0.4727387876,"remaining_time":1.311181166},
{"learn":[0.4279887987],"iteration":265,"passed_time":0.4743519901,"remaining_time":1.308926168},
{"learn":[0.4278261089],"iteration":266,"passed_time":0.4759270251,"remaining_time":1.306571196},
{"learn":[0.4276018437],"iteration":267,"passed_time":0.4774780595,"remaining_time":1.304156491},
{"learn":[0.4275093647],"iteration":268,"passed_time":0.4791638053,"remaining_time":1.302114281},
{"learn":[0.4274066195],"iteration":269,"passed_time":0.4807976332,"remaining_time":1.299934342},
{"learn":[0.427329067],"iteration":270,"passed_time":0.4823882936,"remaining_time":1.29764231},
{"learn":[0.4270770524],"iteration":271,"passed_time":0.4839764121,"remaining_time":1.295348633},
{"learn":[0.4269696778],"iteration":272,"passed_time":0.4856425325,"remaining_time":1.293267843},
{"learn":[0.4267182344],"iteration":273,"passed_time":0.4873204447,"remaining_time":1.291221324},
{"learn":[0.4265221455],"iteration":274,"passed_time":0.4890098572,"remaining_time":1.289207805},
{"learn":[0.4263515818],"iteration":275,"passed_time":0.4905742253,"remaining_time":1.28686862},
{"learn":[0.4263351044],"iteration":276,"passed_time":0.4914595783,"remaining_time":1.282762726},
{"learn":[0.4262020264],"iteration":277,"passed_time":0.4930200296,"remaining_time":1.280433314},
{"learn":[0.426085696],"iteration":278,"passed_time":0.4944991041,"remaining_time":1.277899119},
{"learn":[0.4258649369],"iteration":279,"passed_time":0.4960135961,"remaining_time":1.275463533},
{"learn":[0.425672186],"iteration":280,"passed_time":0.497602423,"remaining_time":1.273224705},
{"learn":[0.4255832912],"iteration":281,"passed_time":0.499238501,"remaining_time":1.271110793},
{"learn":[0.4253605197],"iteration":282,"passed_time":0.5008821208,"remaining_time":1.269019366},
{"learn":[0.425249868],"iteration":283,"passed_time":0.502436197,"remaining_time":1.266705342},
{"learn":[0.4248886113],"iteration":284,"passed_time":0.5039870231,"remaining_time":1.264388497},
{"learn":[0.4246905758],"iteration":285,"passed_time":0.5055005567,"remaining_time":1.261983907},
{"learn":[0.4244069839],"iteration":286,"passed_time":0.507060383,"remaining_time":1.259700533},
{"learn":[0.4243576591],"iteration":287,"passed_time":0.5086652103,"remaining_time":1.257533437},
{"learn":[0.4242049859],"iteration":288,"passed_time":0.5104425414,"remaining_time":1.255794626},
{"learn":[0.4241016884],"iteration":289,"passed_time":0.512059869,"remaining_time":1.253663817},
{"learn":[0.4239843089],"iteration":290,"passed_time":0.5138630757,"remaining_time":1.251989418},
{"learn":[0.4237725031],"iteration":291,"passed_time":0.5154482776,"remaining_time":1.24978555},
{"learn":[0.4236289886],"iteration":292,"passed_time":0.5171573572,"remaining_time":1.247884817},
{"learn":[0.423510748],"iteration":293,"passed_time":0.5187788932,"remaining_time":1.245775165},
{"learn":[0.4234289912],"iteration":294,"passed_time":0.5200142123,"remaining_time":1.242745829},
{"learn":[0.4232585586],"iteration":295,"passed_time":0.5215745803,"remaining_time":1.240501704},
{"learn":[0.4231360022],"iteration":296,"passed_time":0.5232260753,"remaining_time":1.238477882},
{"learn":[0.4229490387],"iteration":297,"passed_time":0.524775943,"remaining_time":1.236217154},
{"learn":[0.4227734366],"iteration":298,"passed_time":0.526350978,"remaining_time":1.234020186},
{"learn":[0.4226608192],"iteration":299,"passed_time":0.5278920122,"remaining_time":1.231748028},
{"learn":[0.4224872315],"iteration":300,"passed_time":0.529477214,"remaining_time":1.229583298},
{"learn":[0.4223865471],"iteration":301,"passed_time":0.5311177505,"remaining_time":1.227550297},
{"learn":[0.4222899381],"iteration":302,"passed_time":0.5326475344,"remaining_time":1.22526512},
{"learn":[0.4220838667],"iteration":303,"passed_time":0.5341960271,"remaining_time":1.223027746},
{"learn":[0.4218472075],"iteration":304,"passed_time":0.535797146,"remaining_time":1.220914808},
{"learn":[0.4217053978],"iteration":305,"passed_time":0.5373356802,"remaining_time":1.218663275},
{"learn":[0.4215494971],"iteration":306,"passed_time":0.5389399241,"remaining_time":1.216564715},
{"learn":[0.4214781287],"iteration":307,"passed_time":0.540527001,"remaining_time":1.214430795},
{"learn":[0.4212743737],"iteration":308,"passed_time":0.5421616623,"remaining_time":1.212406824},
{"learn":[0.4210559522],"iteration":309,"passed_time":0.5436743209,"remaining_time":1.210113811},
{"learn":[0.4208978149],"iteration":310,"passed_time":0.5452772732,"remaining_time":1.208025856},
{"learn":[0.4208121276],"iteration":311,"passed_time":0.5469686441,"remaining_time":1.206135984},
{"learn":[0.4207243742],"iteration":312,"passed_time":0.5485162201,"remaining_time":1.203931767},
{"learn":[0.42069916],"iteration":313,"passed_time":0.5495340344,"remaining_time":1.200574355},
{"learn":[0.4205007414],"iteration":314,"passed_time":0.5510913189,"remaining_time":1.198404932},
{"learn":[0.420287119],"iteration":315,"passed_time":0.5526576037,"remaining_time":1.196258864},
{"learn":[0.4201675626],"iteration":316,"passed_time":0.5541918878,"remaining_time":1.194047506},
{"learn":[0.4200648182],"iteration":317,"passed_time":0.555763256,"remaining_time":1.191919939},
{"learn":[0.4199425851],"iteration":318,"passed_time":0.5573369993,"remaining_time":1.189800929},
{"learn":[0.4197934612],"iteration":319,"passed_time":0.5589979528,"remaining_time":1.18787065},
{"learn":[0.4197065634],"iteration":320,"passed_time":0.5606651148,"remaining_time":1.185955181},
{"learn":[0.419510127],"iteration":321,"passed_time":0.5622456083,"remaining_time":1.183858765},
{"learn":[0.4194262093],"iteration":322,"passed_time":0.5639817718,"remaining_time":1.182091825},
{"learn":[0.4193315211],"iteration":323,"passed_time":0.5655877658,"remaining_time":1.180053487},
{"learn":[0.4193267576],"iteration":324,"passed_time":0.566437993,"remaining_time":1.176448139},
{"learn":[0.4191620107],"iteration":325,"passed_time":0.5680814878,"remaining_time":1.174499763},
{"learn":[0.4189868594],"iteration":326,"passed_time":0.5696647313,"remaining_time":1.172429248},
{"learn":[0.4188518294],"iteration":327,"passed_time":0.5712703086,"remaining_time":1.170407462},
{"learn":[0.4186861468],"iteration":328,"passed_time":0.5728144679,"remaining_time":1.168262942},
{"learn":[0.4184275028],"iteration":329,"passed_time":0.5743760442,"remaining_time":1.166157423},
{"learn":[0.4183442686],"iteration":330,"passed_time":0.5759652879,"remaining_time":1.164111111},
{"learn":[0.4182053856],"iteration":331,"passed_time":0.5777057015,"remaining_time":1.162371713},
{"learn":[0.4179708041],"iteration":332,"passed_time":0.579334696,"remaining_time":1.160409136},
{"learn":[0.4177762681],"iteration":333,"passed_time":0.5809227729,"remaining_time":1.158366966},
{"learn":[0.4176125244],"iteration":334,"passed_time":0.5825868932,"remaining_time":1.15647846},
{"learn":[0.417461842],"iteration":335,"passed_time":0.5841813036,"remaining_time":1.154453529},
{"learn":[0.4173464387],"iteration":336,"passed_time":0.5858392988,"remaining_time":1.152556247},
{"learn":[0.4170072549],"iteration":337,"passed_time":0.5874393343,"remaining_time":1.150546862},
{"learn":[0.4167577787],"iteration":338,"passed_time":0.5890791624,"remaining_time":1.148617482},
{"learn":[0.4167112433],"iteration":339,"passed_time":0.5907316157,"remaining_time":1.146714313},
{"learn":[0.4165615826],"iteration":340,"passed_time":0.5922931087,"remaining_time":1.144636829},
{"learn":[0.4163966059],"iteration":341,"passed_time":0.5938671853,"remaining_time":1.142586573},
{"learn":[0.4163307019],"iteration":342,"passed_time":0.5954751794,"remaining_time":1.140604061},
{"learn":[0.416060341],"iteration":343,"passed_time":0.5970832567,"remaining_time":1.138623885},
{"learn":[0.4159931633],"iteration":344,"passed_time":0.5987567106,"remaining_time":1.136769987},
{"learn":[0.4158325792],"iteration":345,"passed_time":0.6004134973,"remaining_time":1.134885628},
{"learn":[0.4157750451],"iteration":346,"passed_time":0.6020049493,"remaining_time":1.132879631},
{"learn":[0.4156032592],"iteration":347,"passed_time":0.6035967347,"remaining_time":1.130876641},
{"learn":[0.4152708901],"iteration":348,"passed_time":0.6052271459,"remaining_time":1.128948057},
{"learn":[0.4151679952],"iteration":349,"passed_time":0.6067678051,"remaining_time":1.126854495},
{"learn":[0.4149861072],"iteration":350,"passed_time":0.608324923,"remaining_time":1.124794516},
{"learn":[0.4148909289],"iteration":351,"passed_time":0.6098823742,"remaining_time":1.122738007},
{"learn":[0.4146050239],"iteration":352,"passed_time":0.6114182,"remaining_time":1.12064469},
{"learn":[0.4143246345],"iteration":353,"passed_time":0.6130385276,"remaining_time":1.118708726},
{"learn":[0.4141309396],"iteration":354,"passed_time":0.6146216461,"remaining_time":1.116706935},
{"learn":[0.4139701574],"iteration":355,"passed_time":0.6163488928,"remaining_time":1.114968222},
{"learn":[0.4138177258],"iteration":356,"passed_time":0.6180690977,"remaining_time":1.11321689},
{"learn":[0.4136528285],"iteration":357,"passed_time":0.6196480077,"remaining_time":1.111212349},
{"learn":[0.4135373732],"iteration":358,"passed_time":0.6212971277,"remaining_time":1.10933554},
{"learn":[0.4131941972],"iteration":359,"passed_time":0.6228996633,"remaining_time":1.107377179},
{"learn":[0.4130989027],"iteration":360,"passed_time":0.6244442392,"remaining_time":1.105318196},
{"learn":[0.4130314372],"iteration":361,"passed_time":0.6260201909,"remaining_time":1.103317353},
{"learn":[0.4127586579],"iteration":362,"passed_time":0.6276312683,"remaining_time":1.10138049},
{"learn":[0.4126618838],"iteration":363,"passed_time":0.6293243892,"remaining_time":1.099588768},
{"learn":[0.4124661782],"iteration":364,"passed_time":0.6309153829,"remaining_time":1.097619913},
{"learn":[0.4122307837],"iteration":365,"passed_time":0.6324414168,"remaining_time":1.095540596},
{"learn":[0.4119999026],"iteration":366,"passed_time":0.634045119,"remaining_time":1.093598257},
{"learn":[0.4118530377],"iteration":367,"passed_time":0.6356604466,"remaining_time":1.091677723},
{"learn":[0.4116570211],"iteration":368,"passed_time":0.6372035642,"remaining_time":1.089635363},
{"learn":[0.4113764781],"iteration":369,"passed_time":0.6388195167,"remaining_time":1.087719718},
{"learn":[0.4110930326],"iteration":370,"passed_time":0.6404280524,"remaining_time":1.085793113},
{"learn":[0.4109018905],"iteration":371,"passed_time":0.6420487967,"remaining_time":1.083888829},
{"learn":[0.4108262183],"iteration":372,"passed_time":0.6435900393,"remaining_time":1.081852425},
{"learn":[0.4104872974],"iteration":373,"passed_time":0.6452112003,"remaining_time":1.079952437},
{"learn":[0.4103995435],"iteration":374,"passed_time":0.6468200693,"remaining_time":1.078033449},
{"learn":[0.4102231753],"iteration":375,"passed_time":0.6484531889,"remaining_time":1.076156356},
{"learn":[0.4101074741],"iteration":376,"passed_time":0.6500504744,"remaining_time":1.074221341},
{"learn":[0.4099423661],"iteration":377,"passed_time":0.6516273427,"remaining_time":1.072254516},
{"learn":[0.409644425],"iteration":378,"passed_time":0.6531937109,"remaining_time":1.070272545},
{"learn":[0.4095296568],"iteration":379,"passed_time":0.6547858712,"remaining_time":1.068334842},
{"learn":[0.4094346747],"iteration":380,"passed_time":0.6563806566,"remaining_time":1.066403219},
{"learn":[0.409262372],"iteration":381,"passed_time":0.6579188158,"remaining_time":1.064381749},
{"learn":[0.4090436685],"iteration":382,"passed_time":0.6594588916,"remaining_time":1.062365891},
{"learn":[0.4089906762],"iteration":383,"passed_time":0.661082261,"remaining_time":1.060486127},
{"learn":[0.4089878725],"iteration":384,"passed_time":0.6618484863,"remaining_time":1.057238491},
{"learn":[0.4088020109],"iteration":385,"passed_time":0.663409271,"remaining_time":1.055267597},
{"learn":[0.4086092856],"iteration":386,"passed_time":0.6650230568,"remaining_time":1.053382775},
{"learn":[0.4085033139],"iteration":387,"passed_time":0.6667172611,"remaining_time":1.051626195},
{"learn":[0.4083496389],"iteration":388,"passed_time":0.6683531724,"remaining_time":1.049778376},
{"learn":[0.4081464596],"iteration":389,"passed_time":0.6699582497,"remaining_time":1.047883416},
{"learn":[0.4079825004],"iteration":390,"passed_time":0.6715398265,"remaining_time":1.045953336},
{"learn":[0.4076694256],"iteration":391,"passed_time":0.6731443621,"remaining_time":1.044060643},
{"learn":[0.4075326347],"iteration":392,"passed_time":0.6748309829,"remaining_time":1.0422962},
{"learn":[0.4074101369],"iteration":393,"passed_time":0.6764426854,"remaining_time":1.040416922},
{"learn":[0.4072465463],"iteration":394,"passed_time":0.6780273456,"remaining_time":1.03849758},
{"learn":[0.4070841115],"iteration":395,"passed_time":0.6796118807,"remaining_time":1.036579737},
{"learn":[0.406970586],"iteration":396,"passed_time":0.6812136663,"remaining_time":1.034689775},
{"learn":[0.4066690829],"iteration":397,"passed_time":0.6827822428,"remaining_time":1.032751031},
{"learn":[0.4065127289],"iteration":398,"passed_time":0.6844659885,"remaining_time":1.030987617},
{"learn":[0.4063039647],"iteration":399,"passed_time":0.6860663157,"remaining_time":1.029099474},
{"learn":[0.4061279582],"iteration":400,"passed_time":0.6876799765,"remaining_time":1.027232683},
{"learn":[0.4059301212],"iteration":401,"passed_time":0.689278387,"remaining_time":1.025344466},
{"learn":[0.4057748204],"iteration":402,"passed_time":0.6908742975,"remaining_time":1.023453984},
{"learn":[0.4055800319],"iteration":403,"passed_time":0.6924004147,"remaining_time":1.021461998},
{"learn":[0.4054741138],"iteration":404,"passed_time":0.6940069503,"remaining_time":1.019590458},
{"learn":[0.4053212634],"iteration":405,"passed_time":0.6955718184,"remaining_time":1.017659261},
{"learn":[0.4051747446],"iteration":406,"passed_time":0.6971497701,"remaining_time":1.015748928},
{"learn":[0.405083716],"iteration":407,"passed_time":0.6987424722,"remaining_time":1.013861626},
{"learn":[0.404865747],"iteration":408,"passed_time":0.7003595081,"remaining_time":1.012010927},
{"learn":[0.4047950305],"iteration":409,"passed_time":0.7019980861,"remaining_time":1.010192368},
{"learn":[0.4046257184],"iteration":410,"passed_time":0.7036229555,"remaining_time":1.008355038},
{"learn":[0.4044092903],"iteration":411,"passed_time":0.7052114908,"remaining_time":1.006466885},
{"learn":[0.4042708164],"iteration":412,"passed_time":0.7068134847,"remaining_time":1.004599311},
{"learn":[0.4040554485],"iteration":413,"passed_time":0.7083544356,"remaining_time":1.002646617},
{"learn":[0.4038656195],"iteration":414,"passed_time":0.7100572234,"remaining_time":1.000924038},
{"learn":[0.4037575594],"iteration":415,"passed_time":0.7116853012,"remaining_time":0.9990966728},
{"learn":[0.4036583159],"iteration":416,"passed_time":0.7132285438,"remaining_time":0.9971516571},
{"learn":[0.4035868289],"iteration":417,"passed_time":0.7147805366,"remaining_time":0.9952207471},
{"learn":[0.4034083533],"iteration":418,"passed_time":0.7163416129,"remaining_time":0.9933042413},
{"learn":[0.4033060977],"iteration":419,"passed_time":0.7179135228,"remaining_time":0.9914043886},
{"learn":[0.4031153407],"iteration":420,"passed_time":0.7194674323,"remaining_time":0.989481338},
{"learn":[0.4029290631],"iteration":421,"passed_time":0.7211430112,"remaining_time":0.9877266835},
{"learn":[0.4028217867],"iteration":422,"passed_time":0.7226820453,"remaining_time":0.985786147},
{"learn":[0.4025756598],"iteration":423,"passed_time":0.7242370382,"remaining_time":0.983869184},
{"learn":[0.4024081741],"iteration":424,"passed_time":0.7258651993,"remaining_time":0.9820529168},
{"learn":[0.4022086013],"iteration":425,"passed_time":0.7274425677,"remaining_time":0.9801690936},
{"learn":[0.4020739113],"iteration":426,"passed_time":0.7290807291,"remaining_time":0.9783682851},
{"learn":[0.4020016433],"iteration":427,"passed_time":0.7306725977,"remaining_time":0.976506369},
{"learn":[0.4017786569],"iteration":428,"passed_time":0.7322409659,"remaining_time":0.9746144325},
{"learn":[0.4016387839],"iteration":429,"passed_time":0.7338225427,"remaining_time":0.9727415101},
{"learn":[0.4015494495],"iteration":430,"passed_time":0.7354348285,"remaining_time":0.9709104812},
{"learn":[0.4014678344],"iteration":431,"passed_time":0.7370639063,"remaining_time":0.9691025435},
{"learn":[0.4013106971],"iteration":432,"passed_time":0.7386630252,"remaining_time":0.9672562015},
{"learn":[0.4011832838],"iteration":433,"passed_time":0.7403404791,"remaining_time":0.9655131593},
{"learn":[0.4010114081],"iteration":434,"passed_time":0.7419224309,"remaining_time":0.9636463757},
{"learn":[0.4007511286],"iteration":435,"passed_time":0.7435574672,"remaining_time":0.9618495676},
{"learn":[0.4005958313],"iteration":436,"passed_time":0.7451485442,"remaining_time":0.9599968658},
{"learn":[0.4004321195],"iteration":437,"passed_time":0.7467989975,"remaining_time":0.9582215447},
{"learn":[0.4002723291],"iteration":438,"passed_time":0.7484019914,"remaining_time":0.9563861439},
{"learn":[0.4001401942],"iteration":439,"passed_time":0.7499748596,"remaining_time":0.9545134577},
{"learn":[0.399975155],"iteration":440,"passed_time":0.7516398966,"remaining_time":0.9527589619},
{"learn":[0.3998315198],"iteration":441,"passed_time":0.7532373071,"remaining_time":0.9509194963},
{"learn":[0.3995523728],"iteration":442,"passed_time":0.7548123837,"remaining_time":0.9490530423},
{"learn":[0.3994044379],"iteration":443,"passed_time":0.7563939188,"remaining_time":0.9471959884},
{"learn":[0.3992386872],"iteration":444,"passed_time":0.7580443305,"remaining_time":0.9454260751},
{"learn":[0.3991164643],"iteration":445,"passed_time":0.7596709499,"remaining_time":0.9436271441},
{"learn":[0.3989043954],"iteration":446,"passed_time":0.7612506933,"remaining_time":0.941770992},
{"learn":[0.3988052176],"iteration":447,"passed_time":0.7628542289,"remaining_time":0.9399453892},
{"learn":[0.398675981],"iteration":448,"passed_time":0.764554725,"remaining_time":0.9382397628},
{"learn":[0.398444805],"iteration":449,"passed_time":0.7661180931,"remaining_time":0.9363665582},
{"learn":[0.398174786],"iteration":450,"passed_time":0.7680707197,"remaining_time":0.9349685702},
{"learn":[0.3979781249],"iteration":451,"passed_time":0.7696221709,"remaining_time":0.933081747},
{"learn":[0.3977080994],"iteration":452,"passed_time":0.7712727075,"remaining_time":0.9313160508},
{"learn":[0.397565132],"iteration":453,"passed_time":0.7729847038,"remaining_time":0.929624776},
{"learn":[0.3975029275],"iteration":454,"passed_time":0.7745946979,"remaining_time":0.9278112316},
{"learn":[0.397383724],"iteration":455,"passed_time":0.7762080254,"remaining_time":0.9260025566},
{"learn":[0.3972241777],"iteration":456,"passed_time":0.7778229363,"remaining_time":0.9241966179},
{"learn":[0.3969926446],"iteration":457,"passed_time":0.7794581392,"remaining_time":0.9224155272},
{"learn":[0.3968157888],"iteration":458,"passed_time":0.7810714251,"remaining_time":0.9206092396},
{"learn":[0.3965636876],"iteration":459,"passed_time":0.7826173761,"remaining_time":0.9187247458},
{"learn":[0.3963639549],"iteration":460,"passed_time":0.7842422871,"remaining_time":0.9169340407},
{"learn":[0.3962356609],"iteration":461,"passed_time":0.7858849486,"remaining_time":0.9151647237},
{"learn":[0.3960718152],"iteration":462,"passed_time":0.7874393164,"remaining_time":0.9132935484},
{"learn":[0.3958599573],"iteration":463,"passed_time":0.7890130181,"remaining_time":0.9114460726},
{"learn":[0.3957433236],"iteration":464,"passed_time":0.7905753027,"remaining_time":0.9095866386},
{"learn":[0.3955920377],"iteration":465,"passed_time":0.7921380458,"remaining_time":0.9077290052},
{"learn":[0.395409935],"iteration":466,"passed_time":0.7936921636,"remaining_time":0.9058627906},
{"learn":[0.3952461211],"iteration":467,"passed_time":0.7952765738,"remaining_time":0.9040323446},
{"learn":[0.3950908224],"iteration":468,"passed_time":0.7968664841,"remaining_time":0.9022091749},
{"learn":[0.3949474317],"iteration":469,"passed_time":0.7984204353,"remaining_time":0.9003464483},
{"learn":[0.3948393453],"iteration":470,"passed_time":0.800077472,"remaining_time":0.8986008125},
{"learn":[0.3947336349],"iteration":471,"passed_time":0.8016876745,"remaining_time":0.8968031613},
{"learn":[0.394572618],"iteration":472,"passed_time":0.8032835432,"remaining_time":0.8949903325},
{"learn":[0.3944447432],"iteration":473,"passed_time":0.8050188734,"remaining_time":0.8933331802},
{"learn":[0.3943191677],"iteration":474,"passed_time":0.8066987441,"remaining_time":0.8916144013},
{"learn":[0.3941881125],"iteration":475,"passed_time":0.8083943234,"remaining_time":0.8899130787},
{"learn":[0.3939788141],"iteration":476,"passed_time":0.8099844003,"remaining_time":0.8880961035},
{"learn":[0.3939039597],"iteration":477,"passed_time":0.8115412266,"remaining_time":0.8862437663},
{"learn":[0.3937817412],"iteration":478,"passed_time":0.8132089719,"remaining_time":0.8845133077},
{"learn":[0.3936454264],"iteration":479,"passed_time":0.8148496334,"remaining_time":0.8827537695},
{"learn":[0.3935173939],"iteration":480,"passed_time":0.8165215455,"remaining_time":0.8810284451},
{"learn":[0.3933163568],"iteration":481,"passed_time":0.8181300395,"remaining_time":0.8792351877},
{"learn":[0.3931572879],"iteration":482,"passed_time":0.8199624552,"remaining_time":0.8776823796},
{"learn":[0.3930198809],"iteration":483,"passed_time":0.8216032,"remaining_time":0.8759240727},
{"learn":[0.3929339428],"iteration":484,"passed_time":0.8232188608,"remaining_time":0.8741396151},
{"learn":[0.3926397538],"iteration":485,"passed_time":0.8248370634,"remaining_time":0.8723585403},
{"learn":[0.3925350834],"iteration":486,"passed_time":0.8264251404,"remaining_time":0.8705464004},
{"learn":[0.3923923807],"iteration":487,"passed_time":0.8279983836,"remaining_time":0.8687196156},
{"learn":[0.392246779],"iteration":488,"passed_time":0.8296594205,"remaining_time":0.8669856112},
{"learn":[0.3921188287],"iteration":489,"passed_time":0.8312941651,"remaining_time":0.8652245392},
{"learn":[0.3919465367],"iteration":490,"passed_time":0.8329435351,"remaining_time":0.8634791433},
{"learn":[0.3918210222],"iteration":491,"passed_time":0.8345359454,"remaining_time":0.8616753258},
{"learn":[0.3916905628],"iteration":492,"passed_time":0.8361316059,"remaining_time":0.8598757083},
{"learn":[0.3915612578],"iteration":493,"passed_time":0.8376741401,"remaining_time":0.8580224998},
{"learn":[0.3914319023],"iteration":494,"passed_time":0.839291426,"remaining_time":0.8562468084},
{"learn":[0.3912688348],"iteration":495,"passed_time":0.8409611714,"remaining_time":0.8545250613},
{"learn":[0.3910073913],"iteration":496,"passed_time":0.8425762906,"remaining_time":0.8527482378},
{"learn":[0.3908971486],"iteration":497,"passed_time":0.8441630342,"remaining_time":0.8509434602},
{"learn":[0.3907548781],"iteration":498,"passed_time":0.8458036956,"remaining_time":0.8491936904},
{"learn":[0.390573039],"iteration":499,"passed_time":0.8474486905,"remaining_time":0.8474486905},
{"learn":[0.390442373],"iteration":500,"passed_time":0.8490230171,"remaining_time":0.8456337036},
{"learn":[0.3901949449],"iteration":501,"passed_time":0.8506145108,"remaining_time":0.8438367059},
{"learn":[0.3900088727],"iteration":502,"passed_time":0.8522059211,"remaining_time":0.8420404429},
{"learn":[0.3898922785],"iteration":503,"passed_time":0.8538840417,"remaining_time":0.8403303267},
{"learn":[0.3897969198],"iteration":504,"passed_time":0.855490244,"remaining_time":0.8385498431},
{"learn":[0.3896187932],"iteration":505,"passed_time":0.8570882378,"remaining_time":0.8367620346},
{"learn":[0.3894341913],"iteration":506,"passed_time":0.858702982,"remaining_time":0.8349912626},
{"learn":[0.3893207983],"iteration":507,"passed_time":0.8603287264,"remaining_time":0.8332317587},
{"learn":[0.3892410882],"iteration":508,"passed_time":0.8619571376,"remaining_time":0.8314753528},
{"learn":[0.3891305861],"iteration":509,"passed_time":0.8635623399,"remaining_time":0.8296971501},
{"learn":[0.388922636],"iteration":510,"passed_time":0.8652098765,"remaining_time":0.8279601362},
{"learn":[0.3887887837],"iteration":511,"passed_time":0.8667943283,"remaining_time":0.8261633442},
{"learn":[0.3886570588],"iteration":512,"passed_time":0.8687716222,"remaining_time":0.8247403119},
{"learn":[0.3885027772],"iteration":513,"passed_time":0.8703630742,"remaining_time":0.8229502998},
{"learn":[0.3883285095],"iteration":514,"passed_time":0.872004694,"remaining_time":0.8212083041},
{"learn":[0.3881991606],"iteration":515,"passed_time":0.8735873125,"remaining_time":0.8194113551},
{"learn":[0.3880344243],"iteration":516,"passed_time":0.8752704748,"remaining_time":0.817709167},
{"learn":[0.3879284718],"iteration":517,"passed_time":0.8769218865,"remaining_time":0.8159775083},
{"learn":[0.3877168404],"iteration":518,"passed_time":0.8791771033,"remaining_time":0.8148057547},
{"learn":[0.3875638001],"iteration":519,"passed_time":0.8807687636,"remaining_time":0.8130173202},
{"learn":[0.3874616628],"iteration":520,"passed_time":0.882437009,"remaining_time":0.8113000524},
{"learn":[0.3873400308],"iteration":521,"passed_time":0.8840103356,"remaining_time":0.8094960544},
{"learn":[0.3872175869],"iteration":522,"passed_time":0.8856185379,"remaining_time":0.8077247468},
{"learn":[0.3871059373],"iteration":523,"passed_time":0.8872763664,"remaining_time":0.805999142},
{"learn":[0.3869784616],"iteration":524,"passed_time":0.8889584871,"remaining_time":0.804295774},
{"learn":[0.3868207585],"iteration":525,"passed_time":0.8906158156,"remaining_time":0.8025701456},
{"learn":[0.3867465906],"iteration":526,"passed_time":0.8922453517,"remaining_time":0.8008198318},
{"learn":[0.3866067195],"iteration":527,"passed_time":0.8939337642,"remaining_time":0.7991226074},
{"learn":[0.3864737845],"iteration":528,"passed_time":0.8955091325,"remaining_time":0.7973247664},
{"learn":[0.3862907808],"iteration":529,"passed_time":0.8970878759,"remaining_time":0.7955307579},
{"learn":[0.3861844117],"iteration":530,"passed_time":0.8986944949,"remaining_time":0.793762181},
{"learn":[0.3860102361],"iteration":531,"passed_time":0.9002933221,"remaining_time":0.7919873585},
{"learn":[0.3858817731],"iteration":532,"passed_time":0.9018919826,"remaining_time":0.7902130504},
{"learn":[0.3857249689],"iteration":533,"passed_time":0.9036151875,"remaining_time":0.788548085},
{"learn":[0.3855683621],"iteration":534,"passed_time":0.905182389,"remaining_time":0.78674731},
{"learn":[0.3853402154],"iteration":535,"passed_time":0.9068019666,"remaining_time":0.7849927472},
{"learn":[0.385174939],"iteration":536,"passed_time":0.908411794,"remaining_time":0.7832302805},
{"learn":[0.3850711524],"iteration":537,"passed_time":0.9101169985,"remaining_time":0.781550285},
{"learn":[0.3849462496],"iteration":538,"passed_time":0.9118136195,"remaining_time":0.7798628546},
{"learn":[0.3848176014],"iteration":539,"passed_time":0.9134678646,"remaining_time":0.7781392921},
{"learn":[0.3847058767],"iteration":540,"passed_time":0.9151126928,"remaining_time":0.7764079963},
{"learn":[0.3845931692],"iteration":541,"passed_time":0.9167384372,"remaining_time":0.7746608934},
{"learn":[0.3844415134],"iteration":542,"passed_time":0.9183029719,"remaining_time":0.7728627222},
{"learn":[0.3843705343],"iteration":543,"passed_time":0.9200513024,"remaining_time":0.7712194741},
{"learn":[0.3841989373],"iteration":544,"passed_time":0.9216343376,"remaining_time":0.7694378415},
{"learn":[0.384064175],"iteration":545,"passed_time":0.9232775824,"remaining_time":0.7677070007},
{"learn":[0.3839400036],"iteration":546,"passed_time":0.9248106998,"remaining_time":0.7658852779},
{"learn":[0.3837894355],"iteration":547,"passed_time":0.9263669426,"remaining_time":0.7640836826},
{"learn":[0.3836456699],"iteration":548,"passed_time":0.9279969788,"remaining_time":0.7623436019},
{"learn":[0.3834917218],"iteration":549,"passed_time":0.9296423904,"remaining_time":0.7606165012},
{"learn":[0.3833769647],"iteration":550,"passed_time":0.9312645514,"remaining_time":0.7588707506},
{"learn":[0.3831994242],"iteration":551,"passed_time":0.9328466698,"remaining_time":0.7570929494},
{"learn":[0.3830228973],"iteration":552,"passed_time":0.9344037044,"remaining_time":0.7552955802},
{"learn":[0.3827889565],"iteration":553,"passed_time":0.9359250299,"remaining_time":0.7534703309},
{"learn":[0.3826339811],"iteration":554,"passed_time":0.9375406907,"remaining_time":0.7517218151},
{"learn":[0.3824045687],"iteration":555,"passed_time":0.9390924335,"remaining_time":0.7499227347},
{"learn":[0.382173437],"iteration":556,"passed_time":0.9406803021,"remaining_time":0.7481532744},
{"learn":[0.3820339502],"iteration":557,"passed_time":0.9422521287,"remaining_time":0.7463717578},
{"learn":[0.3818977933],"iteration":558,"passed_time":0.9438280803,"remaining_time":0.7445942458},
{"learn":[0.3817713489],"iteration":559,"passed_time":0.9454040737,"remaining_time":0.7428174864},
{"learn":[0.3816679342],"iteration":560,"passed_time":0.9470776108,"remaining_time":0.7411177739},
{"learn":[0.3814984099],"iteration":561,"passed_time":0.9487090637,"remaining_time":0.7393853557},
{"learn":[0.3813197132],"iteration":562,"passed_time":0.9503498085,"remaining_time":0.7376605085},
{"learn":[0.3811638915],"iteration":563,"passed_time":0.9519756362,"remaining_time":0.735924428},
{"learn":[0.3810576069],"iteration":564,"passed_time":0.9536185477,"remaining_time":0.7342018907},
{"learn":[0.380902061],"iteration":565,"passed_time":0.9552241667,"remaining_time":0.7324510395},
{"learn":[0.3807903316],"iteration":566,"passed_time":0.9568864953,"remaining_time":0.7307440078},
{"learn":[0.3806740112],"iteration":567,"passed_time":0.9586872436,"remaining_time":0.7291424106},
{"learn":[0.3805557508],"iteration":568,"passed_time":0.9602549867,"remaining_time":0.7273636191},
{"learn":[0.3804830092],"iteration":569,"passed_time":0.9620229843,"remaining_time":0.7257366373},
{"learn":[0.3803159302],"iteration":570,"passed_time":0.9636470204,"remaining_time":0.7240010013},
{"learn":[0.3801671536],"iteration":571,"passed_time":0.9652436808,"remaining_time":0.7222452717},
{"learn":[0.3800419915],"iteration":572,"passed_time":0.9668913007,"remaining_time":0.7205280723},
{"learn":[0.3798752296],"iteration":573,"passed_time":0.9686021304,"remaining_time":0.7188580271},
{"learn":[0.3797038944],"iteration":574,"passed_time":0.9702652923,"remaining_time":0.7171526074},
{"learn":[0.3795431522],"iteration":575,"passed_time":0.971856786,"remaining_time":0.7153945786},
{"learn":[0.379395893],"iteration":576,"passed_time":0.9734899889,"remaining_time":0.7136677042},
{"learn":[0.3792418148],"iteration":577,"passed_time":0.9751304837,"remaining_time":0.7119464777},
{"learn":[0.3790964295],"iteration":578,"passed_time":0.976692935,"remaining_time":0.7101687835},
{"learn":[0.3789618207],"iteration":579,"passed_time":0.9782880121,"remaining_time":0.708415457},
{"learn":[0.3788456266],"iteration":580,"passed_time":0.9799021313,"remaining_time":0.7066764079},
{"learn":[0.3787575157],"iteration":581,"passed_time":0.9815358759,"remaining_time":0.7049518834},
{"learn":[0.3786577867],"iteration":582,"passed_time":0.9831199527,"remaining_time":0.7031921446},
{"learn":[0.37858856],"iteration":583,"passed_time":0.9848839919,"remaining_time":0.7015611997},
{"learn":[0.3784954495],"iteration":584,"passed_time":0.9866360724,"remaining_time":0.6999213163},
{"learn":[0.3783502763],"iteration":585,"passed_time":0.9885693654,"remaining_time":0.6984090738},
{"learn":[0.3782574094],"iteration":586,"passed_time":0.9901501505,"remaining_time":0.6966473801},
{"learn":[0.3780685462],"iteration":587,"passed_time":0.9918098123,"remaining_time":0.6949415692},
{"learn":[0.3779112112],"iteration":588,"passed_time":0.9939094006,"remaining_time":0.6935428924},
{"learn":[0.37779117],"iteration":589,"passed_time":0.9962151601,"remaining_time":0.6922851113},
{"learn":[0.3776809994],"iteration":590,"passed_time":0.9977878617,"remaining_time":0.6905164728},
{"learn":[0.3774706409],"iteration":591,"passed_time":0.9993062287,"remaining_time":0.6887110495},
{"learn":[0.3773824887],"iteration":592,"passed_time":1.000873305,"remaining_time":0.6869400257},
{"learn":[0.3772424604],"iteration":593,"passed_time":1.002593343,"remaining_time":0.6852742381},
{"learn":[0.3771243612],"iteration":594,"passed_time":1.004245297,"remaining_time":0.6835619247},
{"learn":[0.3769370834],"iteration":595,"passed_time":1.005833707,"remaining_time":0.681806741},
{"learn":[0.3767852537],"iteration":596,"passed_time":1.007468202,"remaining_time":0.6800832249},
{"learn":[0.3766234682],"iteration":597,"passed_time":1.009087654,"remaining_time":0.6783498947},
{"learn":[0.3764873792],"iteration":598,"passed_time":1.010721232,"remaining_time":0.6766264008},
{"learn":[0.3764328741],"iteration":599,"passed_time":1.01241327,"remaining_time":0.6749421798},
{"learn":[0.3763609203],"iteration":600,"passed_time":1.014002472,"remaining_time":0.6731896609},
{"learn":[0.3762079722],"iteration":601,"passed_time":1.015612341,"remaining_time":0.6714513482},
{"learn":[0.3760502997],"iteration":602,"passed_time":1.017259377,"remaining_time":0.6697379317},
{"learn":[0.3759515402],"iteration":603,"passed_time":1.018855246,"remaining_time":0.6679911879},
{"learn":[0.3758372174],"iteration":604,"passed_time":1.020463282,"remaining_time":0.6662528865},
{"learn":[0.3757074747],"iteration":605,"passed_time":1.022056901,"remaining_time":0.6645056416},
{"learn":[0.3755818549],"iteration":606,"passed_time":1.023663145,"remaining_time":0.6627670771},
{"learn":[0.3755290592],"iteration":607,"passed_time":1.025267097,"remaining_time":0.6610274703},
{"learn":[0.3753404394],"iteration":608,"passed_time":1.026930634,"remaining_time":0.6593265645},
{"learn":[0.3752240454],"iteration":609,"passed_time":1.028564545,"remaining_time":0.6576068403},
{"learn":[0.3751541977],"iteration":610,"passed_time":1.030221998,"remaining_time":0.6559023853},
{"learn":[0.3750296209],"iteration":611,"passed_time":1.031787533,"remaining_time":0.6541398087},
{"learn":[0.3749311872],"iteration":612,"passed_time":1.033411069,"remaining_time":0.6524144924},
{"learn":[0.3748213048],"iteration":613,"passed_time":1.035047564,"remaining_time":0.6506976542},
{"learn":[0.3746877911],"iteration":614,"passed_time":1.036700142,"remaining_time":0.648991146},
{"learn":[0.374508571],"iteration":615,"passed_time":1.038229051,"remaining_time":0.6472077203},
{"learn":[0.3744436795],"iteration":616,"passed_time":1.039954173,"remaining_time":0.6455469177},
{"learn":[0.3741893343],"iteration":617,"passed_time":1.04160546,"remaining_time":0.6438402679},
{"learn":[0.3741056935],"iteration":618,"passed_time":1.043144702,"remaining_time":0.6420648328},
{"learn":[0.3739714111],"iteration":619,"passed_time":1.044815906,"remaining_time":0.6403710391},
{"learn":[0.3738680264],"iteration":620,"passed_time":1.046414775,"remaining_time":0.6386331717},
{"learn":[0.3737656619],"iteration":621,"passed_time":1.048090604,"remaining_time":0.6369425211},
{"learn":[0.3736039921],"iteration":622,"passed_time":1.049673472,"remaining_time":0.6351956645},
{"learn":[0.3734482039],"iteration":623,"passed_time":1.051318634,"remaining_time":0.6334868689},
{"learn":[0.3733279346],"iteration":624,"passed_time":1.052961462,"remaining_time":0.631776877},
{"learn":[0.3731362177],"iteration":625,"passed_time":1.054527996,"remaining_time":0.6300215187},
{"learn":[0.3730102968],"iteration":626,"passed_time":1.05612624,"remaining_time":0.6282856262},
{"learn":[0.3728682763],"iteration":627,"passed_time":1.05785007,"remaining_time":0.6266245639},
{"learn":[0.3727775318],"iteration":628,"passed_time":1.059431605,"remaining_time":0.6248793729},
{"learn":[0.3726670031],"iteration":629,"passed_time":1.061040974,"remaining_time":0.6231510485},
{"learn":[0.3725407699],"iteration":630,"passed_time":1.062665885,"remaining_time":0.6214321898},
{"learn":[0.3724120342],"iteration":631,"passed_time":1.064246254,"remaining_time":0.6196876922},
{"learn":[0.3723498475],"iteration":632,"passed_time":1.065950917,"remaining_time":0.6180157764},
{"learn":[0.3722223919],"iteration":633,"passed_time":1.067689539,"remaining_time":0.6163633615},
{"learn":[0.3720702741],"iteration":634,"passed_time":1.0693352,"remaining_time":0.6146572411},
{"learn":[0.3719798674],"iteration":635,"passed_time":1.071002279,"remaining_time":0.6129635684},
{"learn":[0.3718689984],"iteration":636,"passed_time":1.072682191,"remaining_time":0.6112772926},
{"learn":[0.3716571511],"iteration":637,"passed_time":1.074302644,"remaining_time":0.6095572995},
{"learn":[0.3715373647],"iteration":638,"passed_time":1.075964181,"remaining_time":0.6078608282},
{"learn":[0.3714263748],"iteration":639,"passed_time":1.0775818,"remaining_time":0.6061397625},
{"learn":[0.3712313691],"iteration":640,"passed_time":1.079150751,"remaining_time":0.6043917625},
{"learn":[0.3710483719],"iteration":641,"passed_time":1.080723661,"remaining_time":0.6026465277},
{"learn":[0.3709391686],"iteration":642,"passed_time":1.082325697,"remaining_time":0.6009179997},
{"learn":[0.3708418647],"iteration":643,"passed_time":1.083915232,"remaining_time":0.5991829545},
{"learn":[0.3706778871],"iteration":644,"passed_time":1.085578811,"remaining_time":0.597489113},
{"learn":[0.3705624537],"iteration":645,"passed_time":1.087155346,"remaining_time":0.5957476663},
{"learn":[0.3704142115],"iteration":646,"passed_time":1.088708464,"remaining_time":0.5939939531},
{"learn":[0.3703229771],"iteration":647,"passed_time":1.090331208,"remaining_time":0.5922786809},
{"learn":[0.3702114734],"iteration":648,"passed_time":1.091968244,"remaining_time":0.5905714234},
{"learn":[0.3700904132],"iteration":649,"passed_time":1.093621781,"remaining_time":0.5888732668},
{"learn":[0.369915359],"iteration":650,"passed_time":1.095279693,"remaining_time":0.5871775927},
{"learn":[0.369798777],"iteration":651,"passed_time":1.096901021,"remaining_time":0.5854625079},
{"learn":[0.3697000008],"iteration":652,"passed_time":1.098482306,"remaining_time":0.583726432},
{"learn":[0.369524565],"iteration":653,"passed_time":1.100092383,"remaining_time":0.582006062},
{"learn":[0.3693708361],"iteration":654,"passed_time":1.10166421,"remaining_time":0.5802658814},
{"learn":[0.3692489681],"iteration":655,"passed_time":1.103231161,"remaining_time":0.5785236577},
{"learn":[0.3691254668],"iteration":656,"passed_time":1.104782029,"remaining_time":0.5767735706},
{"learn":[0.3689190941],"iteration":657,"passed_time":1.106451024,"remaining_time":0.5750854868},
{"learn":[0.3688021125],"iteration":658,"passed_time":1.108026726,"remaining_time":0.573349186},
{"learn":[0.3686886954],"iteration":659,"passed_time":1.109650845,"remaining_time":0.5716383143},
{"learn":[0.368518218],"iteration":660,"passed_time":1.111441635,"remaining_time":0.5700131835},
{"learn":[0.3683941804],"iteration":661,"passed_time":1.113090713,"remaining_time":0.5683151981},
{"learn":[0.3682387413],"iteration":662,"passed_time":1.114693541,"remaining_time":0.566593851},
{"learn":[0.3680978269],"iteration":663,"passed_time":1.116247492,"remaining_time":0.5648481284},
{"learn":[0.3680103787],"iteration":664,"passed_time":1.117858319,"remaining_time":0.5631316345},
{"learn":[0.3679268043],"iteration":665,"passed_time":1.119437271,"remaining_time":0.5613994722},
{"learn":[0.3678468526],"iteration":666,"passed_time":1.121145892,"remaining_time":0.5597325069},
{"learn":[0.367640831],"iteration":667,"passed_time":1.122734011,"remaining_time":0.5580055263},
{"learn":[0.3675067065],"iteration":668,"passed_time":1.124361047,"remaining_time":0.5562982161},
{"learn":[0.3673732415],"iteration":669,"passed_time":1.126004125,"remaining_time":0.5545990467},
{"learn":[0.3672595811],"iteration":670,"passed_time":1.127553993,"remaining_time":0.5528543422},
{"learn":[0.367169656],"iteration":671,"passed_time":1.129296073,"remaining_time":0.5512040357},
{"learn":[0.3670605162],"iteration":672,"passed_time":1.130935985,"remaining_time":0.5495038142},
{"learn":[0.3669384898],"iteration":673,"passed_time":1.132564271,"remaining_time":0.5477981488},
{"learn":[0.3667633038],"iteration":674,"passed_time":1.13423635,"remaining_time":0.5461137979},
{"learn":[0.3666502164],"iteration":675,"passed_time":1.135822218,"remaining_time":0.5443881637},
{"learn":[0.3665624205],"iteration":676,"passed_time":1.137485005,"remaining_time":0.5426996405},
{"learn":[0.366464476],"iteration":677,"passed_time":1.139055498,"remaining_time":0.5409673605},
{"learn":[0.3662332972],"iteration":678,"passed_time":1.14078112,"remaining_time":0.5393088947},
{"learn":[0.3661142016],"iteration":679,"passed_time":1.142387114,"remaining_time":0.5375939359},
{"learn":[0.3659968538],"iteration":680,"passed_time":1.144070985,"remaining_time":0.5359157769},
{"learn":[0.3658924911],"iteration":681,"passed_time":1.145668603,"remaining_time":0.534197384},
{"learn":[0.3657913161],"iteration":682,"passed_time":1.147304931,"remaining_time":0.5324973107},
{"learn":[0.3656520799],"iteration":683,"passed_time":1.148869758,"remaining_time":0.530764391},
{"learn":[0.3655547942],"iteration":684,"passed_time":1.150540087,"remaining_time":0.5290804777},
{"learn":[0.3654464106],"iteration":685,"passed_time":1.152138247,"remaining_time":0.5273635708},
{"learn":[0.3653471438],"iteration":686,"passed_time":1.153738908,"remaining_time":0.5256481486},
{"learn":[0.3650880014],"iteration":687,"passed_time":1.155337735,"remaining_time":0.5239322285},
{"learn":[0.3649886911],"iteration":688,"passed_time":1.156984563,"remaining_time":0.5222383151},
{"learn":[0.3648944764],"iteration":689,"passed_time":1.158750435,"remaining_time":0.5205980217},
{"learn":[0.3648109169],"iteration":690,"passed_time":1.160324304,"remaining_time":0.5188715049},
{"learn":[0.3647185018],"iteration":691,"passed_time":1.161949465,"remaining_time":0.5171682589},
{"learn":[0.3646120869],"iteration":692,"passed_time":1.163564334,"remaining_time":0.515460679},
{"learn":[0.3644391876],"iteration":693,"passed_time":1.165141411,"remaining_time":0.5137367027},
{"learn":[0.3643106896],"iteration":694,"passed_time":1.16676653,"remaining_time":0.5120342326},
{"learn":[0.3641609809],"iteration":695,"passed_time":1.168365107,"remaining_time":0.5103203917},
{"learn":[0.3640842112],"iteration":696,"passed_time":1.170000144,"remaining_time":0.508622731},
{"learn":[0.3639306886],"iteration":697,"passed_time":1.171791267,"remaining_time":0.506992783},
{"learn":[0.363771003],"iteration":698,"passed_time":1.173363593,"remaining_time":0.5052681568},
{"learn":[0.3636720938],"iteration":699,"passed_time":1.174944587,"remaining_time":0.50354768},
{"learn":[0.3635359279],"iteration":700,"passed_time":1.176558456,"remaining_time":0.5018416238},
{"learn":[0.363448181],"iteration":701,"passed_time":1.178165325,"remaining_time":0.5001328587},
{"learn":[0.3633238517],"iteration":702,"passed_time":1.179803945,"remaining_time":0.4984377974},
{"learn":[0.3632322111],"iteration":703,"passed_time":1.181409689,"remaining_time":0.4967290736},
{"learn":[0.3631323326],"iteration":704,"passed_time":1.183066267,"remaining_time":0.4950419131},
{"learn":[0.3629921224],"iteration":705,"passed_time":1.184628093,"remaining_time":0.4933153817},
{"learn":[0.362867444],"iteration":706,"passed_time":1.186196962,"remaining_time":0.4915922344},
{"learn":[0.3627551861],"iteration":707,"passed_time":1.187798289,"remaining_time":0.48988291},
{"learn":[0.3626745127],"iteration":708,"passed_time":1.189389116,"remaining_time":0.4881695806},
{"learn":[0.3625072292],"iteration":709,"passed_time":1.19100236,"remaining_time":0.4864657526},
{"learn":[0.3624126827],"iteration":710,"passed_time":1.192660355,"remaining_time":0.4847803693},
{"learn":[0.362262194],"iteration":711,"passed_time":1.19423714,"remaining_time":0.4830622139},
{"learn":[0.362118399],"iteration":712,"passed_time":1.195771132,"remaining_time":0.48132723},
{"learn":[0.3620110349],"iteration":713,"passed_time":1.197320708,"remaining_time":0.4795990513},
{"learn":[0.3618823676],"iteration":714,"passed_time":1.19887291,"remaining_time":0.4778724185},
{"learn":[0.3617681946],"iteration":715,"passed_time":1.200519238,"remaining_time":0.4761836083},
{"learn":[0.3616564812],"iteration":716,"passed_time":1.202091731,"remaining_time":0.4744657739},
{"learn":[0.3615612916],"iteration":717,"passed_time":1.203710434,"remaining_time":0.4727664935},
{"learn":[0.3614485196],"iteration":718,"passed_time":1.205327553,"remaining_time":0.4710668183},
{"learn":[0.3613360301],"iteration":719,"passed_time":1.206929714,"remaining_time":0.4693615553},
{"learn":[0.3611426917],"iteration":720,"passed_time":1.208446497,"remaining_time":0.4676235405},
{"learn":[0.3610680411],"iteration":721,"passed_time":1.209976198,"remaining_time":0.4658911122},
{"learn":[0.360904227],"iteration":722,"passed_time":1.211519732,"remaining_time":0.4641645447},
{"learn":[0.3607853014],"iteration":723,"passed_time":1.213068516,"remaining_time":0.4624404842},
{"learn":[0.3606257873],"iteration":724,"passed_time":1.214605592,"remaining_time":0.460712466},
{"learn":[0.3604592287],"iteration":725,"passed_time":1.216126668,"remaining_time":0.4589789352},
{"learn":[0.3603511219],"iteration":726,"passed_time":1.217690786,"remaining_time":0.457262152},
{"learn":[0.3602160624],"iteration":727,"passed_time":1.219295446,"remaining_time":0.455560936},
{"learn":[0.3600902854],"iteration":728,"passed_time":1.220870773,"remaining_time":0.4538490802},
{"learn":[0.3600359982],"iteration":729,"passed_time":1.222511934,"remaining_time":0.4521619484},
{"learn":[0.359947444],"iteration":730,"passed_time":1.224025135,"remaining_time":0.450427854},
{"learn":[0.3597597403],"iteration":731,"passed_time":1.225648712,"remaining_time":0.4487347745},
{"learn":[0.3596572397],"iteration":732,"passed_time":1.227217331,"remaining_time":0.4470218653},
{"learn":[0.3595358614],"iteration":733,"passed_time":1.228802032,"remaining_time":0.445315178},
{"learn":[0.3593663047],"iteration":734,"passed_time":1.230317274,"remaining_time":0.4435837792},
{"learn":[0.3592645672],"iteration":735,"passed_time":1.231983103,"remaining_time":0.4419069826},
{"learn":[0.3590824233],"iteration":736,"passed_time":1.233516637,"remaining_time":0.4401830062},
{"learn":[0.3589244777],"iteration":737,"passed_time":1.235075338,"remaining_time":0.4384684806},
{"learn":[0.3587687961],"iteration":738,"passed_time":1.236620331,"remaining_time":0.4367495351},
{"learn":[0.3586479938],"iteration":739,"passed_time":1.238136365,"remaining_time":0.4350208849},
{"learn":[0.3584968017],"iteration":740,"passed_time":1.239665024,"remaining_time":0.4332972215},
{"learn":[0.3583800674],"iteration":741,"passed_time":1.2412291,"remaining_time":0.4315863987},
{"learn":[0.3582760341],"iteration":742,"passed_time":1.242884762,"remaining_time":0.4299076498},
{"learn":[0.3581849884],"iteration":743,"passed_time":1.244510965,"remaining_time":0.4282188265},
{"learn":[0.3580530666],"iteration":744,"passed_time":1.246058291,"remaining_time":0.4265031733},
{"learn":[0.3579323333],"iteration":745,"passed_time":1.247672326,"remaining_time":0.4248106849},
{"learn":[0.3578528034],"iteration":746,"passed_time":1.250271884,"remaining_time":0.423452191},
{"learn":[0.3577557339],"iteration":747,"passed_time":1.251886545,"remaining_time":0.4217585686},
{"learn":[0.3576051544],"iteration":748,"passed_time":1.253434538,"remaining_time":0.4200428157},
{"learn":[0.3574540016],"iteration":749,"passed_time":1.25504424,"remaining_time":0.41834808},
{"learn":[0.3573269186],"iteration":750,"passed_time":1.256556357,"remaining_time":0.4166212156},
{"learn":[0.3571471309],"iteration":751,"passed_time":1.258155518,"remaining_time":0.4149236281},
{"learn":[0.3569900483],"iteration":752,"passed_time":1.259666759,"remaining_time":0.4131974629},
{"learn":[0.3568947147],"iteration":753,"passed_time":1.261270503,"remaining_time":0.4115020475},
{"learn":[0.3567335235],"iteration":754,"passed_time":1.262790079,"remaining_time":0.409779562},
{"learn":[0.3566374515],"iteration":755,"passed_time":1.264439449,"remaining_time":0.4080995046},
{"learn":[0.3565355404],"iteration":756,"passed_time":1.266066318,"remaining_time":0.4064123056},
{"learn":[0.3564677512],"iteration":757,"passed_time":1.267572768,"remaining_time":0.4046868205},
{"learn":[0.3563935783],"iteration":758,"passed_time":1.269207846,"remaining_time":0.4030027549},
{"learn":[0.3562729129],"iteration":759,"passed_time":1.27074988,"remaining_time":0.4012894359},
{"learn":[0.356147599],"iteration":760,"passed_time":1.272357541,"remaining_time":0.3995971778},
{"learn":[0.3560222686],"iteration":761,"passed_time":1.273916826,"remaining_time":0.3978900322},
{"learn":[0.3558984308],"iteration":762,"passed_time":1.275430318,"remaining_time":0.3961690502},
{"learn":[0.3558290108],"iteration":763,"passed_time":1.276998478,"remaining_time":0.3944654983},
{"learn":[0.3556787039],"iteration":764,"passed_time":1.27854872,"remaining_time":0.3927567964},
{"learn":[0.3555671021],"iteration":765,"passed_time":1.28011463,"remaining_time":0.3910532943},
{"learn":[0.355448203],"iteration":766,"passed_time":1.281713457,"remaining_time":0.3893601506},
{"learn":[0.3553050853],"iteration":767,"passed_time":1.283259617,"remaining_time":0.3876513425},
{"learn":[0.3551560068],"iteration":768,"passed_time":1.284859444,"remaining_time":0.3859590787},
{"learn":[0.3550222396],"iteration":769,"passed_time":1.286449646,"remaining_time":0.3842641799},
{"learn":[0.3548451726],"iteration":770,"passed_time":1.287980888,"remaining_time":0.3825520407},
{"learn":[0.3547001156],"iteration":771,"passed_time":1.289618216,"remaining_time":0.3808717011},
{"learn":[0.3546157943],"iteration":772,"passed_time":1.291136583,"remaining_time":0.3791565386},
{"learn":[0.3545575702],"iteration":773,"passed_time":1.292848829,"remaining_time":0.3774984954},
{"learn":[0.3544402817],"iteration":774,"passed_time":1.294477907,"remaining_time":0.3758161666},
{"learn":[0.3543557637],"iteration":775,"passed_time":1.296092776,"remaining_time":0.3741298736},
{"learn":[0.3542765002],"iteration":776,"passed_time":1.297749772,"remaining_time":0.3724558547},
{"learn":[0.3541573469],"iteration":777,"passed_time":1.299312181,"remaining_time":0.3707548898},
{"learn":[0.3540210444],"iteration":778,"passed_time":1.3008903,"remaining_time":0.3690587371},
{"learn":[0.3539100636],"iteration":779,"passed_time":1.302457543,"remaining_time":0.3673598198},
{"learn":[0.3537962099],"iteration":780,"passed_time":1.304131872,"remaining_time":0.3656912675},
{"learn":[0.3536709895],"iteration":781,"passed_time":1.305715865,"remaining_time":0.3639975174},
{"learn":[0.3536067148],"iteration":782,"passed_time":1.307353777,"remaining_time":0.3623189904},
{"learn":[0.3534541848],"iteration":783,"passed_time":1.308984563,"remaining_time":0.360638604},
{"learn":[0.3533110776],"iteration":784,"passed_time":1.310582348,"remaining_time":0.3589493056},
{"learn":[0.3531924479],"iteration":785,"passed_time":1.312210843,"remaining_time":0.3572686009},
{"learn":[0.3530708143],"iteration":786,"passed_time":1.313821753,"remaining_time":0.35558327},
{"learn":[0.3528699556],"iteration":787,"passed_time":1.31540433,"remaining_time":0.3538905051},
{"learn":[0.3527854279],"iteration":788,"passed_time":1.31705645,"remaining_time":0.3522166172},
{"learn":[0.3527034596],"iteration":789,"passed_time":1.318666111,"remaining_time":0.3505314979},
{"learn":[0.3525770513],"iteration":790,"passed_time":1.320223229,"remaining_time":0.3488326863},
{"learn":[0.3524295197],"iteration":791,"passed_time":1.32185814,"remaining_time":0.3471546631},
{"learn":[0.3522789846],"iteration":792,"passed_time":1.323584595,"remaining_time":0.3455006446},
{"learn":[0.3521116173],"iteration":793,"passed_time":1.325200339,"remaining_time":0.3438177203},
{"learn":[0.3520358919],"iteration":794,"passed_time":1.326812542,"remaining_time":0.3421340517},
{"learn":[0.3518773232],"iteration":795,"passed_time":1.328421953,"remaining_time":0.3404498471},
{"learn":[0.3518109591],"iteration":796,"passed_time":1.330079864,"remaining_time":0.3387781838},
{"learn":[0.3516904754],"iteration":797,"passed_time":1.331707942,"remaining_time":0.3370990029},
{"learn":[0.3515430133],"iteration":798,"passed_time":1.333343604,"remaining_time":0.3354218577},
{"learn":[0.3514693067],"iteration":799,"passed_time":1.334999515,"remaining_time":0.3337498788},
{"learn":[0.3513457191],"iteration":800,"passed_time":1.336633343,"remaining_time":0.3320724536},
{"learn":[0.3512420588],"iteration":801,"passed_time":1.338257379,"remaining_time":0.3303927196},
{"learn":[0.3511804586],"iteration":802,"passed_time":1.339908166,"remaining_time":0.328719687},
{"learn":[0.3510529189],"iteration":803,"passed_time":1.341497493,"remaining_time":0.3270317271},
{"learn":[0.3509398709],"iteration":804,"passed_time":1.343324908,"remaining_time":0.3254016859},
{"learn":[0.3508185356],"iteration":805,"passed_time":1.345018279,"remaining_time":0.3237388911},
{"learn":[0.3506732198],"iteration":806,"passed_time":1.346686066,"remaining_time":0.3220699019},
{"learn":[0.3504892515],"iteration":807,"passed_time":1.348292519,"remaining_time":0.3203863411},
{"learn":[0.3503154795],"iteration":808,"passed_time":1.349911138,"remaining_time":0.3187058435},
{"learn":[0.3501464655],"iteration":809,"passed_time":1.351549341,"remaining_time":0.3170300924},
{"learn":[0.3500521289],"iteration":810,"passed_time":1.35367918,"remaining_time":0.3154690074},
{"learn":[0.3499813834],"iteration":811,"passed_time":1.355422844,"remaining_time":0.3138171116},
{"learn":[0.3498173492],"iteration":812,"passed_time":1.357038588,"remaining_time":0.312135567},
{"learn":[0.3496247586],"iteration":813,"passed_time":1.358644082,"remaining_time":0.3104518418},
{"learn":[0.3495374248],"iteration":814,"passed_time":1.360263743,"remaining_time":0.3087715245},
{"learn":[0.3494103661],"iteration":815,"passed_time":1.361960364,"remaining_time":0.3071087095},
{"learn":[0.3493347968],"iteration":816,"passed_time":1.365164602,"remaining_time":0.3057835032},
{"learn":[0.3492758964],"iteration":817,"passed_time":1.366893598,"remaining_time":0.3041254706},
{"learn":[0.3491648124],"iteration":818,"passed_time":1.36863572,"remaining_time":0.3024701653},
{"learn":[0.3490733022],"iteration":819,"passed_time":1.370292799,"remaining_time":0.3007959802},
{"learn":[0.3489902145],"iteration":820,"passed_time":1.37349937,"remaining_time":0.2994596678},
{"learn":[0.3487921487],"iteration":821,"passed_time":1.377918468,"remaining_time":0.2983813715},
{"learn":[0.3486565486],"iteration":822,"passed_time":1.380356272,"remaining_time":0.2968688459},
{"learn":[0.3485553009],"iteration":823,"passed_time":1.382806368,"remaining_time":0.2953567},
{"learn":[0.3484729733],"iteration":824,"passed_time":1.386681079,"remaining_time":0.2941444714},
{"learn":[0.3482951214],"iteration":825,"passed_time":1.389401557,"remaining_time":0.2926826523},
{"learn":[0.3482094743],"iteration":826,"passed_time":1.39271363,"remaining_time":0.2913415453},
{"learn":[0.3481222623],"iteration":827,"passed_time":1.395219352,"remaining_time":0.2898281746},
{"learn":[0.3480576668],"iteration":828,"passed_time":1.398503384,"remaining_time":0.2884729537},
{"learn":[0.3479267171],"iteration":829,"passed_time":1.400156004,"remaining_time":0.2867789405},
{"learn":[0.3478592197],"iteration":830,"passed_time":1.402082713,"remaining_time":0.2851407684},
{"learn":[0.3477511622],"iteration":831,"passed_time":1.40455056,"remaining_time":0.2836111707},
{"learn":[0.3476664704],"iteration":832,"passed_time":1.406265639,"remaining_time":0.2819284055},
{"learn":[0.3475943737],"iteration":833,"passed_time":1.407807132,"remaining_time":0.2802110118},
{"learn":[0.3475036373],"iteration":834,"passed_time":1.409429043,"remaining_time":0.2785099306},
{"learn":[0.3474330488],"iteration":835,"passed_time":1.411051412,"remaining_time":0.2768091287},
{"learn":[0.3473495029],"iteration":836,"passed_time":1.412717116,"remaining_time":0.2751169533},
{"learn":[0.3472408386],"iteration":837,"passed_time":1.414406862,"remaining_time":0.2734294888},
{"learn":[0.3471342698],"iteration":838,"passed_time":1.416037106,"remaining_time":0.2717306008},
{"learn":[0.347032632],"iteration":839,"passed_time":1.417754603,"remaining_time":0.2700484957},
{"learn":[0.3469190418],"iteration":840,"passed_time":1.41945639,"remaining_time":0.2683633366},
{"learn":[0.3468020656],"iteration":841,"passed_time":1.421026675,"remaining_time":0.2666534616},
{"learn":[0.34671064],"iteration":842,"passed_time":1.422633711,"remaining_time":0.2649507623},
{"learn":[0.3465943954],"iteration":843,"passed_time":1.424228663,"remaining_time":0.2632460562},
{"learn":[0.346496894],"iteration":844,"passed_time":1.425837907,"remaining_time":0.2615442315},
{"learn":[0.3464024182],"iteration":845,"passed_time":1.427481527,"remaining_time":0.2598488832},
{"learn":[0.3462141997],"iteration":846,"passed_time":1.429146147,"remaining_time":0.2581574505},
{"learn":[0.3461338921],"iteration":847,"passed_time":1.430803892,"remaining_time":0.2564648486},
{"learn":[0.346019077],"iteration":848,"passed_time":1.432624808,"remaining_time":0.2548013498},
{"learn":[0.3459249733],"iteration":849,"passed_time":1.434207343,"remaining_time":0.2530954135},
{"learn":[0.3458223862],"iteration":850,"passed_time":1.435750961,"remaining_time":0.2513829531},
{"learn":[0.3457242408],"iteration":851,"passed_time":1.437366413,"remaining_time":0.2496833675},
{"learn":[0.3455929155],"iteration":852,"passed_time":1.439003741,"remaining_time":0.2479877491},
{"learn":[0.3454887384],"iteration":853,"passed_time":1.44060911,"remaining_time":0.2462868034},
{"learn":[0.3453794492],"iteration":854,"passed_time":1.442293189,"remaining_time":0.2445994297},
{"learn":[0.3453082032],"iteration":855,"passed_time":1.443910892,"remaining_time":0.2429008977},
{"learn":[0.3451793061],"iteration":856,"passed_time":1.445527261,"remaining_time":0.2412023318},
{"learn":[0.3450992322],"iteration":857,"passed_time":1.447143172,"remaining_time":0.2395038816},
{"learn":[0.3450308279],"iteration":858,"passed_time":1.448718832,"remaining_time":0.2377990166},
{"learn":[0.3449561729],"iteration":859,"passed_time":1.450372494,"remaining_time":0.2361071501},
{"learn":[0.344886619],"iteration":860,"passed_time":1.452002613,"remaining_time":0.2344115717},
{"learn":[0.3447988109],"iteration":861,"passed_time":1.453565189,"remaining_time":0.232705332},
{"learn":[0.344669896],"iteration":862,"passed_time":1.455200142,"remaining_time":0.2310109148},
{"learn":[0.3445059271],"iteration":863,"passed_time":1.456789844,"remaining_time":0.2293095125},
{"learn":[0.3443400895],"iteration":864,"passed_time":1.458433631,"remaining_time":0.2276168094},
{"learn":[0.3441522424],"iteration":865,"passed_time":1.460049042,"remaining_time":0.2259198286},
{"learn":[0.3440159046],"iteration":866,"passed_time":1.461701662,"remaining_time":0.224228744},
{"learn":[0.3439085065],"iteration":867,"passed_time":1.463345407,"remaining_time":0.2225363982},
{"learn":[0.3437610061],"iteration":868,"passed_time":1.464967651,"remaining_time":0.2208409232},
{"learn":[0.3436849451],"iteration":869,"passed_time":1.466617813,"remaining_time":0.2191497881},
{"learn":[0.3435486166],"iteration":870,"passed_time":1.468304267,"remaining_time":0.2174641222},
{"learn":[0.3434812192],"iteration":871,"passed_time":1.46986301,"remaining_time":0.2157597078},
{"learn":[0.3433791578],"iteration":872,"passed_time":1.471486629,"remaining_time":0.2140650652},
{"learn":[0.3432497217],"iteration":873,"passed_time":1.47312604,"remaining_time":0.2123728617},
{"learn":[0.3431054499],"iteration":874,"passed_time":1.474730076,"remaining_time":0.2106757251},
{"learn":[0.3430032494],"iteration":875,"passed_time":1.476320111,"remaining_time":0.2089768194},
{"learn":[0.3429179173],"iteration":876,"passed_time":1.477947772,"remaining_time":0.207283439},
{"learn":[0.342782154],"iteration":877,"passed_time":1.479567725,"remaining_time":0.2055891372},
{"learn":[0.3426765791],"iteration":878,"passed_time":1.481260346,"remaining_time":0.2039050078},
{"learn":[0.3425674064],"iteration":879,"passed_time":1.482891174,"remaining_time":0.2022124328},
{"learn":[0.342445092],"iteration":880,"passed_time":1.484580878,"remaining_time":0.2005279506},
{"learn":[0.3423490615],"iteration":881,"passed_time":1.486269957,"remaining_time":0.198843373},
{"learn":[0.3422363553],"iteration":882,"passed_time":1.487875951,"remaining_time":0.1971477761},
{"learn":[0.3421119053],"iteration":883,"passed_time":1.489461278,"remaining_time":0.19544967},
{"learn":[0.3420293193],"iteration":884,"passed_time":1.491052188,"remaining_time":0.1937525443},
{"learn":[0.341934069],"iteration":885,"passed_time":1.492709809,"remaining_time":0.1920642417},
{"learn":[0.3418247082],"iteration":886,"passed_time":1.494364637,"remaining_time":0.1903756527},
{"learn":[0.3417347814],"iteration":887,"passed_time":1.496021215,"remaining_time":0.1886873605},
{"learn":[0.341600227],"iteration":888,"passed_time":1.497605251,"remaining_time":0.1869900819},
{"learn":[0.3415582401],"iteration":889,"passed_time":1.499249245,"remaining_time":0.1853004685},
{"learn":[0.3414266421],"iteration":890,"passed_time":1.500854281,"remaining_time":0.1836061915},
{"learn":[0.3413455643],"iteration":891,"passed_time":1.50252111,"remaining_time":0.1819195962},
{"learn":[0.3412151956],"iteration":892,"passed_time":1.50409377,"remaining_time":0.1802217619},
{"learn":[0.3410904562],"iteration":893,"passed_time":1.505725723,"remaining_time":0.1785312378},
{"learn":[0.3409711216],"iteration":894,"passed_time":1.507319258,"remaining_time":0.1768363375},
{"learn":[0.3408564211],"iteration":895,"passed_time":1.508903543,"remaining_time":0.1751405898},
{"learn":[0.3407200242],"iteration":896,"passed_time":1.51048562,"remaining_time":0.1734448371},
{"learn":[0.3406844892],"iteration":897,"passed_time":1.512114989,"remaining_time":0.1717547093},
{"learn":[0.3406228689],"iteration":898,"passed_time":1.513764359,"remaining_time":0.1700669636},
{"learn":[0.3405542681],"iteration":899,"passed_time":1.51538702,"remaining_time":0.1683763356},
{"learn":[0.3404804483],"iteration":900,"passed_time":1.516958847,"remaining_time":0.1666802729},
{"learn":[0.3403327585],"iteration":901,"passed_time":1.518521757,"remaining_time":0.1649835168},
{"learn":[0.3402451901],"iteration":902,"passed_time":1.520090375,"remaining_time":0.1632876704},
{"learn":[0.3401797636],"iteration":903,"passed_time":1.52174162,"remaining_time":0.16160088},
{"learn":[0.3400946681],"iteration":904,"passed_time":1.523356614,"remaining_time":0.1599103628},
{"learn":[0.3399945254],"iteration":905,"passed_time":1.524960025,"remaining_time":0.1582188105},
{"learn":[0.3399320732],"iteration":906,"passed_time":1.526731606,"remaining_time":0.1565446961},
{"learn":[0.3398346362],"iteration":907,"passed_time":1.528279932,"remaining_time":0.1548477464},
{"learn":[0.3397541995],"iteration":908,"passed_time":1.530007845,"remaining_time":0.1531691022},
{"learn":[0.3397166179],"iteration":909,"passed_time":1.531598214,"remaining_time":0.1514767464},
{"learn":[0.3396361948],"iteration":910,"passed_time":1.533248584,"remaining_time":0.1497904763},
{"learn":[0.3395523438],"iteration":911,"passed_time":1.534891078,"remaining_time":0.1481035251},
{"learn":[0.3394260394],"iteration":912,"passed_time":1.536502073,"remaining_time":0.1464136696},
{"learn":[0.3392944612],"iteration":913,"passed_time":1.538230611,"remaining_time":0.1447350465},
{"learn":[0.3392049367],"iteration":914,"passed_time":1.539804354,"remaining_time":0.1430419345},
{"learn":[0.3390740646],"iteration":915,"passed_time":1.541414682,"remaining_time":0.141352438},
{"learn":[0.3389118543],"iteration":916,"passed_time":1.543130845,"remaining_time":0.1396726937},
{"learn":[0.3388020056],"iteration":917,"passed_time":1.544714463,"remaining_time":0.1379810305},
{"learn":[0.3387218421],"iteration":918,"passed_time":1.546259914,"remaining_time":0.1362862384},
{"learn":[0.3385042279],"iteration":919,"passed_time":1.547805365,"remaining_time":0.1345917709},
{"learn":[0.3383992432],"iteration":920,"passed_time":1.549341316,"remaining_time":0.1328968121},
{"learn":[0.3382615338],"iteration":921,"passed_time":1.550938185,"remaining_time":0.1312073518},
{"learn":[0.3380964522],"iteration":922,"passed_time":1.552588846,"remaining_time":0.1295225798},
{"learn":[0.3380174969],"iteration":923,"passed_time":1.554234091,"remaining_time":0.1278374361},
{"learn":[0.3379031798],"iteration":924,"passed_time":1.55580971,"remaining_time":0.1261467332},
{"learn":[0.3378421704],"iteration":925,"passed_time":1.55746933,"remaining_time":0.1244629918},
{"learn":[0.3377584191],"iteration":926,"passed_time":1.559129575,"remaining_time":0.1227793516},
{"learn":[0.3376605182],"iteration":927,"passed_time":1.560765445,"remaining_time":0.1210938707},
{"learn":[0.3375776096],"iteration":928,"passed_time":1.562405606,"remaining_time":0.1194088246},
{"learn":[0.3374405341],"iteration":929,"passed_time":1.564023142,"remaining_time":0.117722172},
{"learn":[0.3373430862],"iteration":930,"passed_time":1.565648428,"remaining_time":0.1160362422},
{"learn":[0.3372670091],"iteration":931,"passed_time":1.567340716,"remaining_time":0.1143553312},
{"learn":[0.3371340297],"iteration":932,"passed_time":1.568915167,"remaining_time":0.1126659338},
{"learn":[0.3370032468],"iteration":933,"passed_time":1.570568829,"remaining_time":0.1109823798},
{"learn":[0.3367971214],"iteration":934,"passed_time":1.57232916,"remaining_time":0.1093063052},
{"learn":[0.3366527785],"iteration":935,"passed_time":1.573919778,"remaining_time":0.1076184464},
{"learn":[0.3365677415],"iteration":936,"passed_time":1.575477563,"remaining_time":0.1059285875},
{"learn":[0.3364970984],"iteration":937,"passed_time":1.577058806,"remaining_time":0.1042405608},
{"learn":[0.3363322375],"iteration":938,"passed_time":1.578644717,"remaining_time":0.1025530647},
{"learn":[0.3362237178],"iteration":939,"passed_time":1.58023471,"remaining_time":0.1008660453},
{"learn":[0.3361523231],"iteration":940,"passed_time":1.581839496,"remaining_time":0.09918015967},
{"learn":[0.3360324326],"iteration":941,"passed_time":1.583447323,"remaining_time":0.09749463348},
{"learn":[0.3359309183],"iteration":942,"passed_time":1.5850149,"remaining_time":0.09580683911},
{"learn":[0.3358585382],"iteration":943,"passed_time":1.58668452,"remaining_time":0.09412535288},
{"learn":[0.3357714947],"iteration":944,"passed_time":1.588259847,"remaining_time":0.09243840377},
{"learn":[0.3357201101],"iteration":945,"passed_time":1.589812756,"remaining_time":0.09075041103},
{"learn":[0.3356467784],"iteration":946,"passed_time":1.591359207,"remaining_time":0.08906234211},
{"learn":[0.3355405523],"iteration":947,"passed_time":1.592906575,"remaining_time":0.08737462225},
{"learn":[0.3354185616],"iteration":948,"passed_time":1.594607446,"remaining_time":0.08569544757},
{"learn":[0.3353471976],"iteration":949,"passed_time":1.596190189,"remaining_time":0.08401000997},
{"learn":[0.3352961992],"iteration":950,"passed_time":1.597847768,"remaining_time":0.08232864419},
{"learn":[0.3352025687],"iteration":951,"passed_time":1.599411386,"remaining_time":0.08064259089},
{"learn":[0.3351176671],"iteration":952,"passed_time":1.601003046,"remaining_time":0.07895817752},
{"learn":[0.3350325345],"iteration":953,"passed_time":1.60260529,"remaining_time":0.07727446892},
{"learn":[0.334936818],"iteration":954,"passed_time":1.604221826,"remaining_time":0.07559160437},
{"learn":[0.3348594703],"iteration":955,"passed_time":1.605928072,"remaining_time":0.07391300751},
{"learn":[0.3347834801],"iteration":956,"passed_time":1.607643902,"remaining_time":0.07223478348},
{"learn":[0.3347392467],"iteration":957,"passed_time":1.609340898,"remaining_time":0.07055565524},
{"learn":[0.3346589807],"iteration":958,"passed_time":1.610899683,"remaining_time":0.0688705808},
{"learn":[0.3346118318],"iteration":959,"passed_time":1.612456176,"remaining_time":0.06718567398},
{"learn":[0.3345399428],"iteration":960,"passed_time":1.614247507,"remaining_time":0.0655105648},
{"learn":[0.3344757087],"iteration":961,"passed_time":1.615840751,"remaining_time":0.06382738932},
{"learn":[0.33442341],"iteration":962,"passed_time":1.617455245,"remaining_time":0.06214521709},
{"learn":[0.3343020518],"iteration":963,"passed_time":1.61904328,"remaining_time":0.06046219718},
{"learn":[0.334201863],"iteration":964,"passed_time":1.620579523,"remaining_time":0.05877749564},
{"learn":[0.3341346767],"iteration":965,"passed_time":1.62220685,"remaining_time":0.05709630736},
{"learn":[0.3340019847],"iteration":966,"passed_time":1.623796677,"remaining_time":0.05541395073},
{"learn":[0.3338491071],"iteration":967,"passed_time":1.62535042,"remaining_time":0.0537305924},
{"learn":[0.3337451977],"iteration":968,"passed_time":1.626937955,"remaining_time":0.05204858268},
{"learn":[0.3336784145],"iteration":969,"passed_time":1.628612618,"remaining_time":0.0503694624},
{"learn":[0.3335793748],"iteration":970,"passed_time":1.630162194,"remaining_time":0.04868661546},
{"learn":[0.3334926851],"iteration":971,"passed_time":1.631826481,"remaining_time":0.04700734718},
{"learn":[0.3334440139],"iteration":972,"passed_time":1.633376348,"remaining_time":0.04532493464},
{"learn":[0.3333216623],"iteration":973,"passed_time":1.634933258,"remaining_time":0.04364298224},
{"learn":[0.3332305251],"iteration":974,"passed_time":1.636545502,"remaining_time":0.04196270518},
{"learn":[0.3331681848],"iteration":975,"passed_time":1.638086203,"remaining_time":0.04028080827},
{"learn":[0.3330557423],"iteration":976,"passed_time":1.639713489,"remaining_time":0.03860123874},
{"learn":[0.3329086293],"iteration":977,"passed_time":1.641330942,"remaining_time":0.03692155492},
{"learn":[0.33287946],"iteration":978,"passed_time":1.642953353,"remaining_time":0.0352421046},
{"learn":[0.3328191236],"iteration":979,"passed_time":1.64456318,"remaining_time":0.03356251388},
{"learn":[0.3327596352],"iteration":980,"passed_time":1.646184758,"remaining_time":0.03188329296},
{"learn":[0.3326009729],"iteration":981,"passed_time":1.647791543,"remaining_time":0.03020391831},
{"learn":[0.3324886911],"iteration":982,"passed_time":1.64941808,"remaining_time":0.02852503291},
{"learn":[0.3323529835],"iteration":983,"passed_time":1.65102699,"remaining_time":0.02684596732},
{"learn":[0.3322774368],"iteration":984,"passed_time":1.652683152,"remaining_time":0.02516776374},
{"learn":[0.3321520182],"iteration":985,"passed_time":1.654252812,"remaining_time":0.02348837664},
{"learn":[0.3320442855],"iteration":986,"passed_time":1.655806388,"remaining_time":0.02180900004},
{"learn":[0.3319451597],"iteration":987,"passed_time":1.657390715,"remaining_time":0.0201302516},
{"learn":[0.3318777946],"iteration":988,"passed_time":1.658995625,"remaining_time":0.01845192303},
{"learn":[0.3317579038],"iteration":989,"passed_time":1.660543618,"remaining_time":0.01677316786},
{"learn":[0.331676436],"iteration":990,"passed_time":1.662161946,"remaining_time":0.01509531535},
{"learn":[0.3315809595],"iteration":991,"passed_time":1.663769856,"remaining_time":0.01341749884},
{"learn":[0.3315139203],"iteration":992,"passed_time":1.665344058,"remaining_time":0.01173958551},
{"learn":[0.331388965],"iteration":993,"passed_time":1.666968886,"remaining_time":0.01006218643},
{"learn":[0.3313382596],"iteration":994,"passed_time":1.668576005,"remaining_time":0.008384804045},
{"learn":[0.3311928325],"iteration":995,"passed_time":1.670196916,"remaining_time":0.006707618136},
{"learn":[0.3311527231],"iteration":996,"passed_time":1.671836702,"remaining_time":0.005030601913},
{"learn":[0.3310530405],"iteration":997,"passed_time":1.673460488,"remaining_time":0.003353628233},
{"learn":[0.3309809406],"iteration":998,"passed_time":1.675030273,"remaining_time":0.00167670698},
{"learn":[0.3309269251],"iteration":999,"passed_time":1.676724686,"remaining_time":0}
]}